placement/verilog/placement.v
module placement(out, clk, reset);
	input clk, reset;
	output reg out;
	//Parameter (constantes recebidas):
	parameter n = 4, n_node = 14, n_edge = 15, size_offset = 28;
	//Registradores:
	reg [4-1:0] state;
	reg [32-1:0] i, j;
	reg [32-1:0] pos_a_X, pos_a_Y, pos_b_X, pos_b_Y;
	reg [32-1:0] a, b;
	reg [32-1:0] xi, xj;
	reg [32-1:0] sum;
	reg [32-1:0] diff_pos_x, diff_pos_y;
	//Memórias:
	reg [32-1:0] e_a [n_edge-1:0];
	reg [32-1:0] e_b [n_edge-1:0];
	reg [32-1:0] pos_X [n_node-1:0];
	reg [32-1:0] pos_Y [n_node-1:0];
	reg [32-1:0] grid [n*n-1:0];
	reg [32-1:0] offset_x [size_offset-1:0];
	reg [32-1:0] offset_y [size_offset-1:0];
	always @(reset) begin
		state <= 0;
		sum <= 0;
	end
	always @(posedge clk) begin
		if(~reset) begin
			case (state)
				0: //Inicializações
				begin
					e_a[0] = 0; e_b[0] = 4;
					e_a[1] = 1; e_b[1] = 5;
					e_a[2] = 2; e_b[2] = 6;
					e_a[3] = 3; e_b[3] = 7;
					e_a[4] = 4; e_b[4] = 8;
					e_a[5] = 5; e_b[5] = 9;
					e_a[6] = 6; e_b[6] = 10;
					e_a[7] = 7; e_b[7] = 4;
					e_a[8] = 7; e_b[8] = 5;
					e_a[9] = 7; e_b[9] = 6;
					e_a[10] = 8; e_b[10] = 11;
					e_a[11] = 9; e_b[11] = 11;
					e_a[12] = 10; e_b[12] = 12;
					e_a[13] = 11; e_b[13] = 13;
					e_a[14] = 12; e_b[14] = 13;

					offset_x[0] = 0; offset_y[0] = 1;
					offset_x[1] = 1; offset_y[1] = 0;
					offset_x[2] = 0; offset_y[2] = -1;
					offset_x[3] = -1; offset_y[3] = 0;
					offset_x[4] = -1; offset_y[4] = 1;
					offset_x[5] = 1; offset_y[5] = 1;
					offset_x[6] = 1; offset_y[6] = -1;
					offset_x[7] = -1; offset_y[7] = -1;
					offset_x[8] = 0; offset_y[8] = 2;
					offset_x[9] = 2; offset_y[9] = 0;
					offset_x[10] = 0; offset_y[10] = -2;
					offset_x[11] = -2; offset_y[11] = 0;
					offset_x[12] = -1; offset_y[12] = 2;
					offset_x[13] = 1; offset_y[13] = 2;
					offset_x[14] = 1; offset_y[14] = -2;
					offset_x[15] = -1; offset_y[15] = -2;
					offset_x[16] = -2; offset_y[16] = 1;
					offset_x[17] = 2; offset_y[17] = 1;
					offset_x[18] = 2; offset_y[18] = -1;
					offset_x[19] = -2; offset_y[19] = -1;
					offset_x[20] = 0; offset_y[20] = 4;
					offset_x[21] = 4; offset_y[21] = 0;
					offset_x[22] = 0; offset_y[22] = -4;
					offset_x[23] = -4; offset_y[23] = 0;
					offset_x[24] = 1; offset_y[24] = 3;
					offset_x[25] = 1; offset_y[25] = -3;
					offset_x[26] = -1; offset_y[26] = -3;
					offset_x[27] = -1; offset_y[27] = 3;

					for(i=0; i<n; i++) begin
						for(j=0; j<n; j++) begin
							grid[i*n+j] = -1;
						end
					end
					for(i=0; i<n_node; i++) begin
					  pos_X[i] = -1;
					  pos_Y[i] = -1;
					end
					a = e_a[0];
					pos_X[a] = 0;
					pos_Y[a] = 0;
					grid[pos_X[0]*n+pos_Y[0]] = a;
					i=0;
					j=0;
					state = 1;
				end
				1://Leitura das memórias
				begin
					if(i == n_edge) begin
						i=0;
						state = 4;
					end
					else begin
						a = e_a[i];
						b = e_b[i];
						pos_a_X = pos_X[a];
						pos_a_Y = pos_Y[a];
						pos_b_X = pos_X[b];
						pos_b_Y = pos_Y[b];
						if(i==0) begin
							state = 3;
						end
						else begin
							state = 2;
						end
					end
				end
				2://Posição X de a
				begin
					if(pos_a_X != -1) begin
	          state = 3;
					 	j=0;
					end
					else begin
						pos_X[a] = pos_X[i-1] + offset_x[j];
						pos_Y[a] = pos_Y[i-1] + offset_y[j];
						xi = pos_X[a];
						xj = pos_Y[a];
						j++;
						if(grid[xi*n+xj] == -1 && xi < n && xi >= 0 && xj < n && xj >= 0) begin
							grid[xi*n+xj] = a;
							pos_a_X = xi;
							pos_a_Y = xj;
						end
						else if(j > size_offset) begin
							$display("No solution\n");
							out = 0;
							state = 5;
						end
						if(pos_a_X == -1) begin
							state = 2;
						end
						else begin
							state = 3;
							j=0;
						end
					end
				end
				3://Posição X de b
				begin
					if(pos_b_X != -1) begin
						state = 1;
						j=0;
						i++;
					end
					else begin
						xi = pos_a_X + offset_x[j];
						xj = pos_a_Y + offset_y[j];
						j++;
						if(grid[xi*n+xj] == -1 && xi < n && xi >= 0 && xj < n && xj >= 0) begin
							grid[xi*n+xj] = b;
							pos_b_X = xi;
							pos_b_Y = xj;
							pos_X[b] = xi;
							pos_Y[b] = xj;
							state = 1;
							j=0;
							i++;
						end
						else if(j > size_offset) begin
							$display("No solution\n");
							out = 0;
							state = 5;
						end
						else if(pos_b_X == -1) begin
							state = 3;
						end
						else begin
							state = 1;
							j=0;
							i++;
						end
					end
				end
				4://Evaluation
				begin
					if(i == n_edge) begin
					 	state = 5;
					end
					else begin
						a = e_a[i];
						b = e_b[i];
						diff_pos_x = pos_X[a]-pos_X[b];
						if($signed(diff_pos_x) < 0) begin
							diff_pos_x *= -1;
						end
						diff_pos_y = pos_Y[a]-pos_Y[b];
						if($signed(diff_pos_y) < 0) begin
							diff_pos_y *= -1;
						end
						if (diff_pos_x + diff_pos_y > 0) begin
							sum += diff_pos_x + diff_pos_y - 1;
						end
						i++;
					end
				end
				5: //Exibe o grid OBS: display existe apenas na simulação
				begin
					for(i=0; i<n; i++) begin
						for(j=0; j<n; j++) begin
							$display("%d", $signed(grid[i*n+j]));
						end
						$display("\n");
					end
					$display("\nEvaluation = %d\n", sum);
					out = 1;
					$finish;
				end
			endcase
		end
	end
endmodule

module test;
	reg clk = 0;
	reg reset = 1;
	initial begin
    $dumpfile("placement.vcd");
    $dumpvars(0, test);
		#1 reset = 0;
	end
	always #1 clk = !clk;
	wire out;
	placement p1 (out, clk, reset);
endmodule

placement/verilog/placement.vcd
$date
	Sat Jan 25 15:06:06 2020
$end
$version
	Icarus Verilog
$end
$timescale
	1s
$end
$scope module test $end
$var wire 1 ! out $end
$var reg 1 " clk $end
$var reg 1 # reset $end
$scope module p1 $end
$var wire 1 " clk $end
$var wire 1 # reset $end
$var reg 32 $ a [31:0] $end
$var reg 32 % b [31:0] $end
$var reg 32 & diff_pos_x [31:0] $end
$var reg 32 ' diff_pos_y [31:0] $end
$var reg 32 ( i [31:0] $end
$var reg 32 ) j [31:0] $end
$var reg 1 ! out $end
$var reg 32 * pos_a_X [31:0] $end
$var reg 32 + pos_a_Y [31:0] $end
$var reg 32 , pos_b_X [31:0] $end
$var reg 32 - pos_b_Y [31:0] $end
$var reg 4 . state [3:0] $end
$var reg 32 / sum [31:0] $end
$var reg 32 0 xi [31:0] $end
$var reg 32 1 xj [31:0] $end
$upscope $end
$upscope $end
$enddefinitions $end
#0
$dumpvars
bx 1
bx 0
b0 /
b0 .
bx -
bx ,
bx +
bx *
bx )
bx (
bx '
bx &
bx %
bx $
1#
0"
x!
$end
#1
b0 .
b0 $
b0 )
b0 (
1"
0#
#2
0"
#3
b1 .
b0 (
b0 )
1"
#4
0"
#5
b11 .
b11111111111111111111111111111111 -
b11111111111111111111111111111111 ,
b0 +
b0 *
b100 %
1"
#6
0"
#7
b1 (
b1 .
b1 -
b0 ,
b0 )
b1 1
b0 0
1"
#8
0"
#9
b10 .
b11111111111111111111111111111111 -
b11111111111111111111111111111111 ,
b11111111111111111111111111111111 +
b11111111111111111111111111111111 *
b101 %
b1 $
1"
#10
0"
#11
b1 )
1"
#12
0"
#13
b11 .
b0 +
b1 *
b0 )
b0 1
b1 0
1"
#14
0"
#15
b10 (
b1 .
b1 -
b1 ,
b0 )
b1 1
1"
#16
0"
#17
b10 .
b11111111111111111111111111111111 -
b11111111111111111111111111111111 ,
b11111111111111111111111111111111 +
b11111111111111111111111111111111 *
b110 %
b10 $
1"
#18
0"
#19
b1 )
1"
#20
0"
#21
b11 .
b0 +
b10 *
b0 )
b0 1
b10 0
1"
#22
0"
#23
b11 (
b1 .
b1 -
b10 ,
b0 )
b1 1
1"
#24
0"
#25
b10 .
b11111111111111111111111111111111 -
b11111111111111111111111111111111 ,
b11111111111111111111111111111111 +
b11111111111111111111111111111111 *
b111 %
b11 $
1"
#26
0"
#27
b1 )
1"
#28
0"
#29
b11 .
b0 +
b11 *
b0 )
b0 1
b11 0
1"
#30
0"
#31
b100 (
b1 .
b1 -
b11 ,
b0 )
b1 1
1"
#32
0"
#33
b10 .
b11111111111111111111111111111111 -
b11111111111111111111111111111111 ,
b1 +
b0 *
b1000 %
b100 $
1"
#34
0"
#35
b11 .
1"
#36
0"
#37
b101 (
b1 .
b10 -
b0 ,
b0 )
b10 1
b0 0
1"
#38
0"
#39
b10 .
b11111111111111111111111111111111 -
b11111111111111111111111111111111 ,
b1 *
b1001 %
b101 $
1"
#40
0"
#41
b11 .
1"
#42
0"
#43
b110 (
b1 .
b10 -
b1 ,
b0 )
b1 0
1"
#44
0"
#45
b10 .
b11111111111111111111111111111111 -
b11111111111111111111111111111111 ,
b10 *
b1010 %
b110 $
1"
#46
0"
#47
b11 .
1"
#48
0"
#49
b111 (
b1 .
b10 -
b10 ,
b0 )
b10 0
1"
#50
0"
#51
b10 .
b1 -
b0 ,
b11 *
b100 %
b111 $
1"
#52
0"
#53
b11 .
1"
#54
0"
#55
b1000 (
b1 .
1"
#56
0"
#57
b10 .
b1 ,
b101 %
1"
#58
0"
#59
b11 .
1"
#60
0"
#61
b1001 (
b1 .
1"
#62
0"
#63
b10 .
b10 ,
b110 %
1"
#64
0"
#65
b11 .
1"
#66
0"
#67
b1010 (
b1 .
1"
#68
0"
#69
b10 .
b11111111111111111111111111111111 -
b11111111111111111111111111111111 ,
b10 +
b0 *
b1011 %
b1000 $
1"
#70
0"
#71
b11 .
1"
#72
0"
#73
b1011 (
b1 .
b11 -
b0 ,
b0 )
b11 1
b0 0
1"
#74
0"
#75
b10 .
b1 *
b1001 $
1"
#76
0"
#77
b11 .
1"
#78
0"
#79
b1100 (
b1 .
1"
#80
0"
#81
b10 .
b11111111111111111111111111111111 -
b11111111111111111111111111111111 ,
b10 *
b1100 %
b1010 $
1"
#82
0"
#83
b11 .
1"
#84
0"
#85
b1101 (
b1 .
b11 -
b10 ,
b0 )
b10 0
1"
#86
0"
#87
b10 .
b11111111111111111111111111111111 -
b11111111111111111111111111111111 ,
b11 +
b0 *
b1101 %
b1011 $
1"
#88
0"
#89
b11 .
1"
#90
0"
#91
b1 )
b100 1
b0 0
1"
#92
0"
#93
b1110 (
b1 .
b11 -
b1 ,
b0 )
b11 1
b1 0
1"
#94
0"
#95
b10 .
b10 *
b1100 $
1"
#96
0"
#97
b11 .
1"
#98
0"
#99
b1111 (
b1 .
1"
#100
0"
#101
b100 .
b0 (
1"
#102
0"
#103
b1 (
b1 '
b0 &
b100 %
b0 $
1"
#104
0"
#105
b10 (
b1 '
b101 %
b1 $
1"
#106
0"
#107
b11 (
b1 '
b110 %
b10 $
1"
#108
0"
#109
b100 (
b1 '
b111 %
b11 $
1"
#110
0"
#111
b101 (
b1 '
b1000 %
b100 $
1"
#112
0"
#113
b110 (
b1 '
b1001 %
b101 $
1"
#114
0"
#115
b111 (
b1 '
b1010 %
b110 $
1"
#116
0"
#117
b1000 (
b10 /
b0 '
b11 &
b100 %
b111 $
1"
#118
0"
#119
b1001 (
b11 /
b10 &
b101 %
1"
#120
0"
#121
b1010 (
b1 &
b110 %
1"
#122
0"
#123
b1011 (
b1 '
b0 &
b1011 %
b1000 $
1"
#124
0"
#125
b1100 (
b100 /
b1 '
b1 &
b1001 $
1"
#126
0"
#127
b1101 (
b1 '
b0 &
b1100 %
b1010 $
1"
#128
0"
#129
b1110 (
b0 '
b1 &
b1101 %
b1011 $
1"
#130
0"
#131
b1111 (
b1100 $
1"
#132
0"
#133
b101 .
1"
#134
0"
#135
1!
b100 )
b100 (
1"
