placement/verilog/placement.v
module placement(out, clk, reset);
	input clk, reset;
	output reg out;
	//COLOCAR COMO parameter(constante recebida)
	parameter n = 4, n_node = 14, n_edge = 15, size_offset = 28;

	reg [0:2] state;
	reg [0:63] i, j;
	reg [0:63] pos_a_X, pos_a_Y, pos_b_X, pos_b_Y;
	reg [0:63] a, b;
	reg [0:63] xi, xj;

	reg [0:63] sum;
	reg [0:63] diff_pos_x, diff_pos_y;
	reg [0:n_edge] e_a, e_b;
	reg [0:n_node] pos_X, pos_Y;
	reg [0:n*n-1] grid;
	reg [0:size_offset] offset_x, offset_y;

	always @(reset) begin
		state = 0;
		sum = 0;
	end

	always @(posedge clk) begin
		if(~reset) begin
			case (state)
				0: //INICIALIZACOES
				begin
					e_a[0] = 0; e_b[0] = 4;
					e_a[1] = 1; e_b[1] = 5;
					e_a[2] = 2; e_b[2] = 6;
					e_a[3] = 3; e_b[3] = 7;
					e_a[4] = 4; e_b[4] = 8;
					e_a[5] = 5; e_b[5] = 9;
					e_a[6] = 6; e_b[6] = 10;
					e_a[7] = 7; e_b[7] = 4;
					e_a[8] = 7; e_b[8] = 5;
					e_a[9] = 7; e_b[9] = 6;
					e_a[10] = 8; e_b[10] = 11;
					e_a[11] = 9; e_b[11] = 11;
					e_a[12] = 10; e_b[12] = 12;
					e_a[13] = 11; e_b[13] = 13;
					e_a[14] = 12; e_b[14] = 13;

					offset_x[0] = 0; offset_y[0] = 1;
					offset_x[1] = 1; offset_y[1] = 0;
					offset_x[2] = 0; offset_y[2] = -1;
					offset_x[3] = -1; offset_y[3] = 0;
					offset_x[4] = -1; offset_y[4] = 1;
					offset_x[5] = 1; offset_y[5] = 1;
					offset_x[6] = 1; offset_y[6] = -1;
					offset_x[7] = -1; offset_y[7] = -1;
					offset_x[8] = 0; offset_y[8] = 2;
					offset_x[9] = 2; offset_y[9] = 0;
					offset_x[10] = 0; offset_y[10] = -2;
					offset_x[11] = -2; offset_y[11] = 0;
					offset_x[12] = -1; offset_y[12] = 2;
					offset_x[13] = 1; offset_y[13] = 2;
					offset_x[14] = 1; offset_y[14] = -2;
					offset_x[15] = -1; offset_y[15] = -2;
					offset_x[16] = -2; offset_y[16] = 1;
					offset_x[17] = 2; offset_y[17] = 1;
					offset_x[18] = 2; offset_y[18] = -1;
					offset_x[19] = -2; offset_y[19] = -1;
					offset_x[20] = 0; offset_y[20] = 4;
					offset_x[21] = 4; offset_y[21] = 0;
					offset_x[22] = 0; offset_y[22] = -4;
					offset_x[23] = -4; offset_y[23] = 0;
					offset_x[24] = 1; offset_y[24] = 3;
					offset_x[25] = 1; offset_y[25] = -3;
					offset_x[26] = -1; offset_y[26] = -3;
					offset_x[27] = -1; offset_y[27] = 3;

					for(i=0; i<n; i++)begin
						for(j=0; j<n; j++)begin
							grid[i*n+j] = -1;
							//$display("%d ", grid[i*n+j]);
						end
					end

					for(i=0; i<n_node; i++)begin
					  pos_X[i] = -1;
					  pos_Y[i] = -1;
					end

					a = e_a[0];
					pos_X[a] = 0;
					pos_Y[a] = 0;

					//Talvez possa ser eliminado
					//grid[pos_X[0]*n+pos_Y[0]] = a;
					grid[0] = a;

					i=0;
					j=0;
					state = 1;
				end
				1://Leitura das memórias
				begin
					if(i == n_edge)begin
						i=0;
						state = 4;
						//break;
					end
					else begin
						a = e_a[i];
						b = e_b[i];
						pos_a_X = pos_X[a];
						pos_a_Y = pos_Y[a];
						pos_b_X = pos_X[b];
						pos_b_Y = pos_Y[b];

						if(i==0)begin
							state = 3;
						end
						else begin
							state = 2;
						end
					end
				end
				2://Posição X de a
				begin
					if(pos_a_X != -1)begin
	          state = 3;
					 	j=0;
						//break;
					end
					else begin
						pos_X[a] = pos_X[i-1] + offset_x[j];
						pos_Y[a] = pos_Y[i-1] + offset_y[j];

						xi = pos_X[a];
						xj = pos_Y[a];
						j++;

						if(grid[xi*n+xj] == -1 && xi < n && xi >= 0 && xj < n && xj >= 0)begin
							grid[xi*n+xj] = a;
							pos_a_X = xi;
							pos_a_Y = xj;
						end
						else if(j > size_offset)begin
							$display("No solution\n");
							out = 0;
							state = 5;
						end

						else if(pos_a_X == -1)begin
							state = 2;
						end
						else begin
							state = 3;
							j=0;
						end
					end
				end
				3://Posição X de bs
				begin
					if(pos_b_X != -1)begin
						state = 1;
						j=0;
						i++;
					  //break;
					end
					else begin
						xi = pos_a_X + offset_x[j];
						xj = pos_a_Y + offset_y[j];
						j++;
						if(grid[xi*n+xj] == -1 && xi < n && xi >= 0 && xj < n && xj >= 0)begin
							grid[xi*n+xj] = b;
							pos_b_X = xi;
							pos_b_Y = xj;
							pos_X[b] = xi;
							pos_Y[b] = xj;
							state = 1;
							j=0;
							i++;
						  	//break; SWITCH ??? É NECESSARIO ?
						end
						else if(j > size_offset)begin
							$display("No solution\n");
							out = 0;
							state = 5;
						end
						else if(pos_b_X == -1)begin
							state = 3;
						end
						else begin
							state = 1;
							j=0;
							i++;
						end
					end
				end
				4://Evaluation
				begin
					if(i == n_edge)begin
					 	state = 5;
					 	//break;
					end
					else begin
						a = e_a[i];
						b = e_b[i];
						diff_pos_x = pos_X[a]-pos_X[b];

						if(diff_pos_x < 0)
							diff_pos_x *= -1;

						diff_pos_y = pos_Y[a]-pos_Y[b];

						if(diff_pos_y < 0)
							diff_pos_y *= -1;

						if (diff_pos_x + diff_pos_y > 0)
							sum += diff_pos_x + diff_pos_y - 1;
						i++;
					end
				end
				5: //Exibe a grid OBS: display existe apenas na simulacao
				begin
					for(i=0; i<n; i++)begin
						for(j=0; j<n; j++)begin
							$display("%d ", grid[i*n+j]);
					  	end
					 	$display("\n");
					 end
					 $display("Evaluation = %d\n", sum);
					 out = 1;
				end
			endcase
		end
	end

endmodule

module test;
	/* Make a regular pulsing clock. */
	reg clk = 0;
	reg reset = 1;
	wire out;

	initial begin
    		$dumpfile("placement.vcd");
    		$dumpvars(0, test);
		//$monitor("reset = %d\nclk = %d\n", reset, clk);
		#4 reset = 0;
		#200 $finish;
  	end

	always #1 clk = !clk;

	placement p1 (out, clk, reset);
endmodule // test

placement/verilog/placement.vcd
$date
	Fri Jan 24 01:21:11 2020
$end
$version
	Icarus Verilog
$end
$timescale
	1s
$end
$scope module test $end
$var wire 1 ! out $end
$var reg 1 " clk $end
$var reg 1 # reset $end
$scope module p1 $end
$var wire 1 " clk $end
$var wire 1 # reset $end
$var reg 64 $ a [0:63] $end
$var reg 64 % b [0:63] $end
$var reg 64 & diff_pos_x [0:63] $end
$var reg 64 ' diff_pos_y [0:63] $end
$var reg 16 ( e_a [0:15] $end
$var reg 16 ) e_b [0:15] $end
$var reg 16 * grid [0:15] $end
$var reg 64 + i [0:63] $end
$var reg 64 , j [0:63] $end
$var reg 29 - offset_x [0:28] $end
$var reg 29 . offset_y [0:28] $end
$var reg 1 ! out $end
$var reg 15 / pos_X [0:14] $end
$var reg 15 0 pos_Y [0:14] $end
$var reg 64 1 pos_a_X [0:63] $end
$var reg 64 2 pos_a_Y [0:63] $end
$var reg 64 3 pos_b_X [0:63] $end
$var reg 64 4 pos_b_Y [0:63] $end
$var reg 3 5 state [0:2] $end
$var reg 64 6 sum [0:63] $end
$var reg 64 7 xi [0:63] $end
$var reg 64 8 xj [0:63] $end
$upscope $end
$upscope $end
$enddefinitions $end
#0
$dumpvars
bx 8
bx 7
b0 6
b0 5
bx 4
bx 3
bx 2
bx 1
bx 0
bx /
bx .
bx -
bx ,
bx +
bx *
bx )
bx (
bx '
bx &
bx %
bx $
1#
0"
x!
$end
#1
1"
#2
0"
#3
1"
#4
0"
0#
#5
b1 5
b0 $
b1111111111111x 0
b1111111111111x /
b111111111111111 *
b0 ,
b0 +
b1010111100000000111100001111x .
b101111100001111000000001111x -
b10101001011011x )
b10101011101010x (
1"
#6
0"
#7
b11 5
b0 4
b0 3
b0 2
b0 1
b0 %
1"
#8
0"
#9
b1 +
b1 5
1"
#10
0"
#11
b10 5
b1 4
b1 3
b1 2
b1 1
b1 %
b1 $
1"
#12
0"
#13
b11 5
1"
#14
0"
#15
b10 +
b1 5
1"
#16
0"
#17
b10 5
b0 4
b0 3
b0 2
b0 1
b0 %
b0 $
1"
#18
0"
#19
b11 5
1"
#20
0"
#21
b11 +
b1 5
1"
#22
0"
#23
b10 5
b1 4
b1 3
b1 2
b1 1
b1 %
b1 $
1"
#24
0"
#25
b11 5
1"
#26
0"
#27
b100 +
b1 5
1"
#28
0"
#29
b10 5
b0 4
b0 3
b0 2
b0 1
b0 %
b0 $
1"
#30
0"
#31
b11 5
1"
#32
0"
#33
b101 +
b1 5
1"
#34
0"
#35
b10 5
b1 4
b1 3
b1 2
b1 1
b1 %
b1 $
1"
#36
0"
#37
b11 5
1"
#38
0"
#39
b110 +
b1 5
1"
#40
0"
#41
b10 5
b0 4
b0 3
b0 2
b0 1
b0 %
b0 $
1"
#42
0"
#43
b11 5
1"
#44
0"
#45
b111 +
b1 5
1"
#46
0"
#47
b10 5
b1 2
b1 1
b1 $
1"
#48
0"
#49
b11 5
1"
#50
0"
#51
b1000 +
b1 5
1"
#52
0"
#53
b10 5
b1 4
b1 3
b1 %
1"
#54
0"
#55
b11 5
1"
#56
0"
#57
b1001 +
b1 5
1"
#58
0"
#59
b10 5
b0 4
b0 3
b0 %
1"
#60
0"
#61
b11 5
1"
#62
0"
#63
b1010 +
b1 5
1"
#64
0"
#65
b10 5
b1 4
b1 3
b0 2
b0 1
b1 %
b0 $
1"
#66
0"
#67
b11 5
1"
#68
0"
#69
b1011 +
b1 5
1"
#70
0"
#71
b10 5
b1 2
b1 1
b1 $
1"
#72
0"
#73
b11 5
1"
#74
0"
#75
b1100 +
b1 5
1"
#76
0"
#77
b10 5
b0 4
b0 3
b0 2
b0 1
b0 %
b0 $
1"
#78
0"
#79
b11 5
1"
#80
0"
#81
b1101 +
b1 5
1"
#82
0"
#83
b10 5
b1 4
b1 3
b1 2
b1 1
b1 %
b1 $
1"
#84
0"
#85
b11 5
1"
#86
0"
#87
b1110 +
b1 5
1"
#88
0"
#89
b10 5
b0 2
b0 1
b0 $
1"
#90
0"
#91
b11 5
1"
#92
0"
#93
b1111 +
b1 5
1"
#94
0"
#95
b100 5
b0 +
1"
#96
0"
#97
b1 +
b0 '
b0 &
b0 %
1"
#98
0"
#99
b10 +
b1 %
b1 $
1"
#100
0"
#101
b11 +
b0 %
b0 $
1"
#102
0"
#103
b100 +
b1 %
b1 $
1"
#104
0"
#105
b101 +
b0 %
b0 $
1"
#106
0"
#107
b110 +
b1 %
b1 $
1"
#108
0"
#109
b111 +
b0 %
b0 $
1"
#110
0"
#111
b1000 +
b1 6
b1 '
b1 &
b1 $
1"
#112
0"
#113
b1001 +
b0 '
b0 &
b1 %
1"
#114
0"
#115
b1010 +
b10 6
b1 '
b1 &
b0 %
1"
#116
0"
#117
b1011 +
b1111111111111111111111111111111111111111111111111111111111111111 6
b1111111111111111111111111111111111111111111111111111111111111111 '
b1111111111111111111111111111111111111111111111111111111111111111 &
b1 %
b0 $
1"
#118
0"
#119
b1100 +
b0 '
b0 &
b1 $
1"
#120
0"
#121
b1101 +
b0 %
b0 $
1"
#122
0"
#123
b1110 +
b1 %
b1 $
1"
#124
0"
#125
b1111 +
b1111111111111111111111111111111111111111111111111111111111111100 6
b1111111111111111111111111111111111111111111111111111111111111111 '
b1111111111111111111111111111111111111111111111111111111111111111 &
b0 $
1"
#126
0"
#127
b101 5
1"
#128
0"
#129
1!
b100 ,
b100 +
1"
#130
0"
#131
b100 ,
b100 +
1"
#132
0"
#133
b100 ,
b100 +
1"
#134
0"
#135
b100 ,
b100 +
1"
#136
0"
#137
b100 ,
b100 +
1"
#138
0"
#139
b100 ,
b100 +
1"
#140
0"
#141
b100 ,
b100 +
1"
#142
0"
#143
b100 ,
b100 +
1"
#144
0"
#145
b100 ,
b100 +
1"
#146
0"
#147
b100 ,
b100 +
1"
#148
0"
#149
b100 ,
b100 +
1"
#150
0"
#151
b100 ,
b100 +
1"
#152
0"
#153
b100 ,
b100 +
1"
#154
0"
#155
b100 ,
b100 +
1"
#156
0"
#157
b100 ,
b100 +
1"
#158
0"
#159
b100 ,
b100 +
1"
#160
0"
#161
b100 ,
b100 +
1"
#162
0"
#163
b100 ,
b100 +
1"
#164
0"
#165
b100 ,
b100 +
1"
#166
0"
#167
b100 ,
b100 +
1"
#168
0"
#169
b100 ,
b100 +
1"
#170
0"
#171
b100 ,
b100 +
1"
#172
0"
#173
b100 ,
b100 +
1"
#174
0"
#175
b100 ,
b100 +
1"
#176
0"
#177
b100 ,
b100 +
1"
#178
0"
#179
b100 ,
b100 +
1"
#180
0"
#181
b100 ,
b100 +
1"
#182
0"
#183
b100 ,
b100 +
1"
#184
0"
#185
b100 ,
b100 +
1"
#186
0"
#187
b100 ,
b100 +
1"
#188
0"
#189
b100 ,
b100 +
1"
#190
0"
#191
b100 ,
b100 +
1"
#192
0"
#193
b100 ,
b100 +
1"
#194
0"
#195
b100 ,
b100 +
1"
#196
0"
#197
b100 ,
b100 +
1"
#198
0"
#199
b100 ,
b100 +
1"
#200
0"
#201
b100 ,
b100 +
1"
#202
0"
#203
b100 ,
b100 +
1"
