placement/verilog/placement.v
module placement(out, clk, reset);
	input clk, reset;
	output reg out;
	//COLOCAR COMO parameter(constante recebida)
	parameter n = 4, n_node = 14, n_edge = 15, size_offset = 28;

	reg [0:2] state;
	reg [0:63] i, j;
	reg [0:63] pos_a_X, pos_a_Y, pos_b_X, pos_b_Y;
	reg [0:63] a, b;
	reg [0:63] xi, xj;

	reg [0:63] sum;
	reg [0:63] diff_pos_x, diff_pos_y;
	reg [0:n_edge] e_a, e_b;
	reg [0:n_node] pos_X, pos_Y;
	reg [0:n*n-1] grid;
	reg [0:size_offset] offset_x, offset_y;
	always @(reset) begin
		state <= 0;
		sum <= 0;
	end
	always @(posedge clk) begin
		if(~reset) begin
			case (state)
				0: //INICIALIZACOES
				begin
					e_a[0] = 0; e_b[0] = 4;
					e_a[1] = 1; e_b[1] = 5;
					e_a[2] = 2; e_b[2] = 6;
					e_a[3] = 3; e_b[3] = 7;
					e_a[4] = 4; e_b[4] = 8;
					e_a[5] = 5; e_b[5] = 9;
					e_a[6] = 6; e_b[6] = 10;
					e_a[7] = 7; e_b[7] = 4;
					e_a[8] = 7; e_b[8] = 5;
					e_a[9] = 7; e_b[9] = 6;
					e_a[10] = 8; e_b[10] = 11;
					e_a[11] = 9; e_b[11] = 11;
					e_a[12] = 10; e_b[12] = 12;
					e_a[13] = 11; e_b[13] = 13;
					e_a[14] = 12; e_b[14] = 13;

					offset_x[0] = 0; offset_y[0] = 1;
					offset_x[1] = 1; offset_y[1] = 0;
					offset_x[2] = 0; offset_y[2] = -1;
					offset_x[3] = -1; offset_y[3] = 0;
					offset_x[4] = -1; offset_y[4] = 1;
					offset_x[5] = 1; offset_y[5] = 1;
					offset_x[6] = 1; offset_y[6] = -1;
					offset_x[7] = -1; offset_y[7] = -1;
					offset_x[8] = 0; offset_y[8] = 2;
					offset_x[9] = 2; offset_y[9] = 0;
					offset_x[10] = 0; offset_y[10] = -2;
					offset_x[11] = -2; offset_y[11] = 0;
					offset_x[12] = -1; offset_y[12] = 2;
					offset_x[13] = 1; offset_y[13] = 2;
					offset_x[14] = 1; offset_y[14] = -2;
					offset_x[15] = -1; offset_y[15] = -2;
					offset_x[16] = -2; offset_y[16] = 1;
					offset_x[17] = 2; offset_y[17] = 1;
					offset_x[18] = 2; offset_y[18] = -1;
					offset_x[19] = -2; offset_y[19] = -1;
					offset_x[20] = 0; offset_y[20] = 4;
					offset_x[21] = 4; offset_y[21] = 0;
					offset_x[22] = 0; offset_y[22] = -4;
					offset_x[23] = -4; offset_y[23] = 0;
					offset_x[24] = 1; offset_y[24] = 3;
					offset_x[25] = 1; offset_y[25] = -3;
					offset_x[26] = -1; offset_y[26] = -3;
					offset_x[27] = -1; offset_y[27] = 3;

					for(i=0; i<n; i++)begin
						for(j=0; j<n; j++)begin
							grid[i*n+j] = -1;
							//$display("%d ", grid[i*n+j]);
						end
					end

					for(i=0; i<n_node; i++)begin
					  pos_X[i] = -1;
					  pos_Y[i] = -1;
					end

					a = e_a[0];
					pos_X[a] = 0;
					pos_Y[a] = 0;

					//Talvez possa ser eliminado
					//grid[pos_X[0]*n+pos_Y[0]] = a;
					grid[0] = a;

					i=0;
					j=0;
					state = 1;
				end
				1://Leitura das memórias
				begin
					if(i == n_edge)begin
						i=0;
						state = 4;
						//break;
					end
					else begin
						a = e_a[i];
						b = e_b[i];
						pos_a_X = pos_X[a];
						pos_a_Y = pos_Y[a];
						pos_b_X = pos_X[b];
						pos_b_Y = pos_Y[b];

						if(i==0)begin
							state = 3;
						end
						else begin
							state = 2;
						end
					end
				end
				2://Posição X de a
				begin
					if(pos_a_X != -1)begin
	          state = 3;
					 	j=0;
						//break;
					end
					else begin
						pos_X[a] = pos_X[i-1] + offset_x[j];
						pos_Y[a] = pos_Y[i-1] + offset_y[j];

						xi = pos_X[a];
						xj = pos_Y[a];
						j++;

						if(grid[xi*n+xj] == -1 && xi < n && xi >= 0 && xj < n && xj >= 0)begin
							grid[xi*n+xj] = a;
							pos_a_X = xi;
							pos_a_Y = xj;
						end
						else if(j > size_offset)begin
							$display("No solution\n");
							out = 0;
							state = 5;
						end

						else if(pos_a_X == -1)begin
							state = 2;
						end
						else begin
							state = 3;
							j=0;
						end
					end
				end
				3://Posição X de bs
				begin
					if(pos_b_X != -1)begin
						state = 1;
						j=0;
						i++;
					  //break;
					end
					else begin
						xi = pos_a_X + offset_x[j];
						xj = pos_a_Y + offset_y[j];
						j++;
						if(grid[xi*n+xj] == -1 && xi < n && xi >= 0 && xj < n && xj >= 0)begin
							grid[xi*n+xj] = b;
							pos_b_X = xi;
							pos_b_Y = xj;
							pos_X[b] = xi;
							pos_Y[b] = xj;
							state = 1;
							j=0;
							i++;
						  	//break; SWITCH ??? É NECESSARIO ?
						end
						else if(j > size_offset)begin
							$display("No solution\n");
							out = 0;
							state = 5;
						end
						else if(pos_b_X == -1)begin
							state = 3;
						end
						else begin
							state = 1;
							j=0;
							i++;
						end
					end
				end
				4://Evaluation
				begin
					if(i == n_edge)begin
					 	state = 5;
					 	//break;
					end
					else begin
						a = e_a[i];
						b = e_b[i];
						diff_pos_x = pos_X[a]-pos_X[b];

						if(diff_pos_x < 0)
							diff_pos_x *= -1;

						diff_pos_y = pos_Y[a]-pos_Y[b];

						if(diff_pos_y < 0)
							diff_pos_y *= -1;

						if (diff_pos_x + diff_pos_y > 0)
							sum += diff_pos_x + diff_pos_y - 1;
						i++;
					end
				end
				5: //Exibe a grid OBS: display existe apenas na simulacao
				begin
					for(i=0; i<n; i++)begin
						for(j=0; j<n; j++)begin
							$display("%d ", grid[i*n+j]);
					  end
					 	$display("\n");
					 end
					 $display("\nEvaluation = %d\n", sum);
					 out = 1;
				end
			endcase
		end
	end

endmodule

module test;
	/* Make a regular pulsing clock. */
	reg clk = 0;
	reg reset = 1;
	initial begin
    $dumpfile("placement.vcd");
    $dumpvars(0, test);
		$monitor("reset = %d\nclk = %d\n", reset, clk);
		#5 reset = 0;
  end
	always #5 clk = !clk;
	wire out;
	placement p1 (out, clk, reset);
endmodule // test

placement/verilog/placement.vcd
$date
	Thu Jan 23 20:48:25 2020
$end
$version
	Icarus Verilog
$end
$timescale
	1s
$end
$scope module test $end
$var wire 1 ! out $end
$var reg 1 " clk $end
$var reg 1 # reset $end
$scope module p1 $end
$var wire 1 " clk $end
$var wire 1 # reset $end
$var reg 64 $ a [0:63] $end
$var reg 64 % b [0:63] $end
$var reg 64 & diff_pos_x [0:63] $end
$var reg 64 ' diff_pos_y [0:63] $end
$var reg 16 ( e_a [0:15] $end
$var reg 16 ) e_b [0:15] $end
$var reg 16 * grid [0:15] $end
$var reg 64 + i [0:63] $end
$var reg 64 , j [0:63] $end
$var reg 29 - offset_x [0:28] $end
$var reg 29 . offset_y [0:28] $end
$var reg 1 ! out $end
$var reg 15 / pos_X [0:14] $end
$var reg 15 0 pos_Y [0:14] $end
$var reg 64 1 pos_a_X [0:63] $end
$var reg 64 2 pos_a_Y [0:63] $end
$var reg 64 3 pos_b_X [0:63] $end
$var reg 64 4 pos_b_Y [0:63] $end
$var reg 3 5 state [0:2] $end
$var reg 64 6 sum [0:63] $end
$var reg 64 7 xi [0:63] $end
$var reg 64 8 xj [0:63] $end
$upscope $end
$upscope $end
$enddefinitions $end
#0
$dumpvars
bx 8
bx 7
b0 6
b0 5
bx 4
bx 3
bx 2
bx 1
bx 0
bx /
bx .
bx -
bx ,
bx +
bx *
bx )
bx (
bx '
bx &
bx %
bx $
1#
0"
x!
$end
#5
b0 5
b0 $
b1111111111111x 0
b1111111111111x /
b111111111111111 *
b0 ,
b0 +
b1010111100000000111100001111x .
b101111100001111000000001111x -
b10101001011011x )
b10101011101010x (
1"
0#
#10
0"
#15
b1 5
b1111111111111x 0
b1111111111111x /
b0 +
b0 ,
b111111111111111 *
1"
#20
0"
#25
b11 5
b0 4
b0 3
b0 2
b0 1
b0 %
1"
#30
0"
#35
b1 +
b1 5
1"
#40
0"
#45
b10 5
b1 4
b1 3
b1 2
b1 1
b1 %
b1 $
1"
#50
0"
#55
b11 5
1"
#60
0"
#65
b10 +
b1 5
1"
#70
0"
#75
b10 5
b0 4
b0 3
b0 2
b0 1
b0 %
b0 $
1"
#80
0"
#85
b11 5
1"
#90
0"
#95
b11 +
b1 5
1"
#100
0"
#105
b10 5
b1 4
b1 3
b1 2
b1 1
b1 %
b1 $
1"
#110
0"
#115
b11 5
1"
#120
0"
#125
b100 +
b1 5
1"
#130
0"
#135
b10 5
b0 4
b0 3
b0 2
b0 1
b0 %
b0 $
1"
#140
0"
#145
b11 5
1"
#150
0"
#155
b101 +
b1 5
1"
#160
0"
#165
b10 5
b1 4
b1 3
b1 2
b1 1
b1 %
b1 $
1"
#170
0"
#175
b11 5
1"
#180
0"
#185
b110 +
b1 5
1"
#190
0"
#195
b10 5
b0 4
b0 3
b0 2
b0 1
b0 %
b0 $
1"
#200
0"
#205
b11 5
1"
#210
0"
#215
b111 +
b1 5
1"
#220
0"
#225
b10 5
b1 2
b1 1
b1 $
1"
#230
0"
#235
b11 5
1"
#240
0"
#245
b1000 +
b1 5
1"
#250
0"
#255
b10 5
b1 4
b1 3
b1 %
1"
#260
0"
#265
b11 5
1"
#270
0"
#275
b1001 +
b1 5
1"
#280
0"
#285
b10 5
b0 4
b0 3
b0 %
1"
#290
0"
#295
b11 5
1"
#300
0"
#305
b1010 +
b1 5
1"
#310
0"
#315
b10 5
b1 4
b1 3
b0 2
b0 1
b1 %
b0 $
1"
#320
0"
#325
b11 5
1"
#330
0"
#335
b1011 +
b1 5
1"
#340
0"
#345
b10 5
b1 2
b1 1
b1 $
1"
#350
0"
#355
b11 5
1"
#360
0"
#365
b1100 +
b1 5
1"
#370
0"
#375
b10 5
b0 4
b0 3
b0 2
b0 1
b0 %
b0 $
1"
#380
0"
#385
b11 5
1"
#390
0"
#395
b1101 +
b1 5
1"
#400
0"
#405
b10 5
b1 4
b1 3
b1 2
b1 1
b1 %
b1 $
1"
#410
0"
#415
b11 5
1"
#420
0"
#425
b1110 +
b1 5
1"
#430
0"
#435
b10 5
b0 2
b0 1
b0 $
1"
#440
0"
#445
b11 5
1"
#450
0"
#455
b1111 +
b1 5
1"
#460
0"
#465
b100 5
b0 +
1"
#470
0"
#475
b1 +
b0 '
b0 &
b0 %
1"
#480
0"
#485
b10 +
b1 %
b1 $
1"
#490
0"
#495
b11 +
b0 %
b0 $
1"
#500
0"
#505
b100 +
b1 %
b1 $
1"
#510
0"
#515
b101 +
b0 %
b0 $
1"
#520
0"
#525
b110 +
b1 %
b1 $
1"
#530
0"
#535
b111 +
b0 %
b0 $
1"
#540
0"
#545
b1000 +
b1 6
b1 '
b1 &
b1 $
1"
#550
0"
#555
b1001 +
b0 '
b0 &
b1 %
1"
#560
0"
#565
b1010 +
b10 6
b1 '
b1 &
b0 %
1"
#570
0"
#575
b1011 +
b1111111111111111111111111111111111111111111111111111111111111111 6
b1111111111111111111111111111111111111111111111111111111111111111 '
b1111111111111111111111111111111111111111111111111111111111111111 &
b1 %
b0 $
1"
#580
0"
#585
b1100 +
b0 '
b0 &
b1 $
1"
#590
0"
#595
b1101 +
b0 %
b0 $
1"
#600
0"
#605
b1110 +
b1 %
b1 $
1"
#610
0"
#615
b1111 +
b1111111111111111111111111111111111111111111111111111111111111100 6
b1111111111111111111111111111111111111111111111111111111111111111 '
b1111111111111111111111111111111111111111111111111111111111111111 &
b0 $
1"
#620
0"
#625
b101 5
1"
#630
0"
#635
1!
b100 ,
b100 +
1"
#640
0"
#645
b100 ,
b100 +
1"
#650
0"
#655
b100 ,
b100 +
1"
#660
0"
#665
b100 ,
b100 +
1"
#670
0"
#675
b100 ,
b100 +
1"
#680
0"
#685
b100 ,
b100 +
1"
#690
0"
#695
b100 ,
b100 +
1"
#700
0"
#705
b100 ,
b100 +
1"
#710
0"
#715
b100 ,
b100 +
1"
#720
0"
#725
b100 ,
b100 +
1"
#730
0"
#735
b100 ,
b100 +
1"
#740
0"
#745
b100 ,
b100 +
1"
#750
0"
#755
b100 ,
b100 +
1"
#760
0"
#765
b100 ,
b100 +
1"
#770
0"
#775
b100 ,
b100 +
1"
#780
0"
#785
b100 ,
b100 +
1"
#790
0"
#795
b100 ,
b100 +
1"
#800
0"
#805
b100 ,
b100 +
1"
#810
0"
#815
b100 ,
b100 +
1"
#820
0"
#825
b100 ,
b100 +
1"
#830
0"
#835
b100 ,
b100 +
1"
#840
0"
#845
b100 ,
b100 +
1"
#850
0"
#855
b100 ,
b100 +
1"
#860
0"
#865
b100 ,
b100 +
1"
#870
0"
#875
b100 ,
b100 +
1"
#880
0"
#885
b100 ,
b100 +
1"
#890
0"
#895
b100 ,
b100 +
1"
#900
0"
#905
b100 ,
b100 +
1"
#910
0"
#915
b100 ,
b100 +
1"
#920
0"
#925
b100 ,
b100 +
1"
#930
0"
#935
b100 ,
b100 +
1"
#940
0"
#945
b100 ,
b100 +
1"
#950
0"
#955
b100 ,
b100 +
1"
#960
0"
#965
b100 ,
b100 +
1"
#970
0"
#975
b100 ,
b100 +
1"
#980
0"
#985
b100 ,
b100 +
1"
#990
0"
#995
b100 ,
b100 +
1"
#1000
0"
#1005
b100 ,
b100 +
1"
#1010
0"
#1015
b100 ,
b100 +
1"
#1020
0"
#1025
b100 ,
b100 +
1"
#1030
0"
#1035
b100 ,
b100 +
1"
#1040
0"
#1045
b100 ,
b100 +
1"
#1050
0"
#1055
b100 ,
b100 +
1"
#1060
0"
#1065
b100 ,
b100 +
1"
#1070
0"
#1075
b100 ,
b100 +
1"
#1080
0"
#1085
b100 ,
b100 +
1"
#1090
0"
#1095
b100 ,
b100 +
1"
#1100
0"
#1105
b100 ,
b100 +
1"
#1110
0"
#1115
b100 ,
b100 +
1"
#1120
0"
#1125
b100 ,
b100 +
1"
#1130
0"
#1135
b100 ,
b100 +
1"
#1140
0"
#1145
b100 ,
b100 +
1"
#1150
0"
#1155
b100 ,
b100 +
1"
#1160
0"
#1165
b100 ,
b100 +
1"
#1170
0"
#1175
b100 ,
b100 +
1"
#1180
0"
#1185
b100 ,
b100 +
1"
#1190
0"
#1195
b100 ,
b100 +
1"
#1200
0"
#1205
b100 ,
b100 +
1"
#1210
0"
#1215
b100 ,
b100 +
1"
#1220
0"
#1225
b100 ,
b100 +
1"
#1230
0"
#1235
b100 ,
b100 +
1"
#1240
0"
#1245
b100 ,
b100 +
1"
#1250
0"
#1255
b100 ,
b100 +
1"
#1260
0"
#1265
b100 ,
b100 +
1"
#1270
0"
#1275
b100 ,
b100 +
1"
#1280
0"
#1285
b100 ,
b100 +
1"
#1290
0"
#1295
b100 ,
b100 +
1"
#1300
0"
#1305
b100 ,
b100 +
1"
#1310
0"
#1315
b100 ,
b100 +
1"
#1320
0"
#1325
b100 ,
b100 +
1"
#1330
0"
#1335
b100 ,
b100 +
1"
#1340
0"
#1345
b100 ,
b100 +
1"
#1350
0"
#1355
b100 ,
b100 +
1"
#1360
0"
#1365
b100 ,
b100 +
1"
#1370
0"
#1375
b100 ,
b100 +
1"
#1380
0"
#1385
b100 ,
b100 +
1"
#1390
0"
#1395
b100 ,
b100 +
1"
#1400
0"
#1405
b100 ,
b100 +
1"
#1410
0"
#1415
b100 ,
b100 +
1"
#1420
0"
#1425
b100 ,
b100 +
1"
#1430
0"
#1435
b100 ,
b100 +
1"
#1440
0"
#1445
b100 ,
b100 +
1"
#1450
0"
#1455
b100 ,
b100 +
1"
#1460
0"
#1465
b100 ,
b100 +
1"
#1470
0"
#1475
b100 ,
b100 +
1"
#1480
0"
#1485
b100 ,
b100 +
1"
#1490
0"
#1495
b100 ,
b100 +
1"
#1500
0"
#1505
b100 ,
b100 +
1"
#1510
0"
#1515
b100 ,
b100 +
1"
#1520
0"
#1525
b100 ,
b100 +
1"
#1530
0"
#1535
b100 ,
b100 +
1"
#1540
0"
#1545
b100 ,
b100 +
1"
#1550
0"
#1555
b100 ,
b100 +
1"
#1560
0"
#1565
b100 ,
b100 +
1"
#1570
0"
#1575
b100 ,
b100 +
1"
#1580
0"
#1585
b100 ,
b100 +
1"
#1590
0"
#1595
b100 ,
b100 +
1"
#1600
0"
#1605
b100 ,
b100 +
1"
#1610
0"
#1615
b100 ,
b100 +
1"
#1620
0"
#1625
b100 ,
b100 +
1"
#1630
0"
#1635
b100 ,
b100 +
1"
#1640
0"
#1645
b100 ,
b100 +
1"
#1650
0"
#1655
b100 ,
b100 +
1"
#1660
0"
#1665
b100 ,
b100 +
1"
#1670
0"
#1675
b100 ,
b100 +
1"
#1680
0"
#1685
b100 ,
b100 +
1"
#1690
0"
#1695
b100 ,
b100 +
1"
#1700
0"
#1705
b100 ,
b100 +
1"
#1710
0"
#1715
b100 ,
b100 +
1"
#1720
0"
#1725
b100 ,
b100 +
1"
#1730
0"
#1735
b100 ,
b100 +
1"
#1740
0"
#1745
b100 ,
b100 +
1"
#1750
0"
#1755
b100 ,
b100 +
1"
#1760
0"
#1765
b100 ,
b100 +
1"
#1770
0"
#1775
b100 ,
b100 +
1"
#1780
0"
#1785
b100 ,
b100 +
1"
#1790
0"
#1795
b100 ,
b100 +
1"
#1800
0"
#1805
b100 ,
b100 +
1"
#1810
0"
#1815
b100 ,
b100 +
1"
#1820
0"
#1825
b100 ,
b100 +
1"
#1830
0"
#1835
b100 ,
b100 +
1"
#1840
0"
#1845
b100 ,
b100 +
1"
#1850
0"
#1855
b100 ,
b100 +
1"
#1860
0"
#1865
b100 ,
b100 +
1"
#1870
0"
#1875
b100 ,
b100 +
1"
#1880
0"
#1885
b100 ,
b100 +
1"
#1890
0"
#1895
b100 ,
b100 +
1"
#1900
0"
#1905
b100 ,
b100 +
1"
#1910
0"
#1915
b100 ,
b100 +
1"
#1920
0"
#1925
b100 ,
b100 +
1"
#1930
0"
#1935
b100 ,
b100 +
1"
#1940
0"
#1945
b100 ,
b100 +
1"
#1950
0"
#1955
b100 ,
b100 +
1"
#1960
0"
#1965
b100 ,
b100 +
1"
#1970
0"
#1975
b100 ,
b100 +
1"
#1980
0"
#1985
b100 ,
b100 +
1"
#1990
0"
#1995
b100 ,
b100 +
1"
#2000
0"
#2005
b100 ,
b100 +
1"
#2010
0"
#2015
b100 ,
b100 +
1"
#2020
0"
#2025
b100 ,
b100 +
1"
#2030
0"
#2035
b100 ,
b100 +
1"
#2040
0"
#2045
b100 ,
b100 +
1"
#2050
0"
#2055
b100 ,
b100 +
1"
#2060
0"
#2065
b100 ,
b100 +
1"
#2070
0"
#2075
b100 ,
b100 +
1"
#2080
0"
#2085
b100 ,
b100 +
1"
#2090
0"
#2095
b100 ,
b100 +
1"
#2100
0"
#2105
b100 ,
b100 +
1"
#2110
0"
#2115
b100 ,
b100 +
1"
#2120
0"
#2125
b100 ,
b100 +
1"
#2130
0"
#2135
b100 ,
b100 +
1"
#2140
0"
#2145
b100 ,
b100 +
1"
#2150
0"
#2155
b100 ,
b100 +
1"
#2160
0"
#2165
b100 ,
b100 +
1"
#2170
0"
#2175
b100 ,
b100 +
1"
#2180
0"
#2185
b100 ,
b100 +
1"
#2190
0"
#2195
b100 ,
b100 +
1"
#2200
0"
#2205
b100 ,
b100 +
1"
#2210
0"
#2215
b100 ,
b100 +
1"
#2220
0"
#2225
b100 ,
b100 +
1"
#2230
0"
#2235
b100 ,
b100 +
1"
#2240
0"
#2245
b100 ,
b100 +
1"
#2250
0"
#2255
b100 ,
b100 +
1"
#2260
0"
#2265
b100 ,
b100 +
1"
#2270
0"
#2275
b100 ,
b100 +
1"
#2280
0"
#2285
b100 ,
b100 +
1"
#2290
0"
#2295
b100 ,
b100 +
1"
#2300
0"
#2305
b100 ,
b100 +
1"
#2310
0"
#2315
b100 ,
b100 +
1"
#2320
0"
#2325
b100 ,
b100 +
1"
#2330
0"
#2335
b100 ,
b100 +
1"
#2340
0"
#2345
b100 ,
b100 +
1"
#2350
0"
#2355
b100 ,
b100 +
1"
#2360
0"
#2365
b100 ,
b100 +
1"
#2370
0"
#2375
b100 ,
b100 +
1"
#2380
0"
#2385
b100 ,
b100 +
1"
#2390
0"
#2395
b100 ,
b100 +
1"
#2400
0"
#2405
b100 ,
b100 +
1"
#2410
0"
#2415
b100 ,
b100 +
1"
#2420
0"
#2425
b100 ,
b100 +
1"
#2430
0"
#2435
b100 ,
b100 +
1"
#2440
0"
#2445
b100 ,
b100 +
1"
#2450
0"
#2455
b100 ,
b100 +
1"
#2460
0"
#2465
b100 ,
b100 +
1"
#2470
0"
#2475
b100 ,
b100 +
1"
#2480
0"
#2485
b100 ,
b100 +
1"
#2490
0"
#2495
b100 ,
b100 +
1"
#2500
0"
#2505
b100 ,
b100 +
1"
#2510
0"
#2515
b100 ,
b100 +
1"
#2520
0"
#2525
b100 ,
b100 +
1"
#2530
0"
#2535
b100 ,
b100 +
1"
#2540
0"
#2545
b100 ,
b100 +
1"
#2550
0"
#2555
b100 ,
b100 +
1"
#2560
0"
#2565
b100 ,
b100 +
1"
#2570
0"
#2575
b100 ,
b100 +
1"
#2580
0"
#2585
b100 ,
b100 +
1"
#2590
0"
#2595
b100 ,
b100 +
1"
#2600
0"
#2605
b100 ,
b100 +
1"
#2610
0"
#2615
b100 ,
b100 +
1"
#2620
0"
#2625
b100 ,
b100 +
1"
#2630
0"
#2635
b100 ,
b100 +
1"
#2640
0"
#2645
b100 ,
b100 +
1"
#2650
0"
#2655
b100 ,
b100 +
1"
#2660
0"
#2665
b100 ,
b100 +
1"
#2670
0"
#2675
b100 ,
b100 +
1"
#2680
0"
#2685
b100 ,
b100 +
1"
#2690
0"
#2695
b100 ,
b100 +
1"
#2700
0"
#2705
b100 ,
b100 +
1"
#2710
0"
#2715
b100 ,
b100 +
1"
#2720
0"
#2725
b100 ,
b100 +
1"
#2730
0"
#2735
b100 ,
b100 +
1"
#2740
0"
#2745
b100 ,
b100 +
1"
#2750
0"
#2755
b100 ,
b100 +
1"
#2760
0"
#2765
b100 ,
b100 +
1"
#2770
0"
#2775
b100 ,
b100 +
1"
#2780
0"
#2785
b100 ,
b100 +
1"
#2790
0"
#2795
b100 ,
b100 +
1"
#2800
0"
#2805
b100 ,
b100 +
1"
#2810
0"
#2815
b100 ,
b100 +
1"
#2820
0"
#2825
b100 ,
b100 +
1"
#2830
0"
#2835
b100 ,
b100 +
1"
#2840
0"
#2845
b100 ,
b100 +
1"
#2850
0"
#2855
b100 ,
b100 +
1"
#2860
0"
#2865
b100 ,
b100 +
1"
#2870
0"
#2875
b100 ,
b100 +
1"
#2880
0"
#2885
b100 ,
b100 +
1"
#2890
0"
#2895
b100 ,
b100 +
1"
#2900
0"
#2905
b100 ,
b100 +
1"
#2910
0"
#2915
b100 ,
b100 +
1"
#2920
0"
#2925
b100 ,
b100 +
1"
#2930
0"
#2935
b100 ,
b100 +
1"
