placement/verilog/memorias/memoryRAM.v
module memoryRAM #(
  parameter init_file = "mem_file.txt",
  parameter data_depth = 14
  )(clk, read, write, addr, dataRead, dataWrite);
  input clk, read, write;
  input [32-1:0] addr, dataWrite;
  output reg [32-1:0] dataRead;
  reg signed [32-1:0] memRAM [data_depth-1:0];
  always @ (posedge clk) begin
    dataRead <= 0;
    if(read) begin
      dataRead <= memRAM[addr];
    end
    if(write) begin
      memRAM[addr] <= dataWrite;
    end
  end
  initial begin
    dataRead = 0;
    $readmemh(init_file, memRAM);
  end
endmodule

placement/verilog/memorias/memoryROM.v
module memoryROM #(
  parameter init_file = "mem_file.txt",
  parameter data_depth = 15
  )(clk, read, addr, data);
  input clk, read;
  input [32-1:0] addr;
  output reg [32-1:0] data;
  reg  [32-1:0] memROM [data_depth-1:0];
  always @ (posedge clk) begin
    if(read) begin
      data <= memROM[addr];
    end
  end
  initial begin
    data = 0;
    $readmemh(init_file, memROM);
  end
endmodule

placement/verilog/placement.v
`include "memorias/memoryROM.v"
`include "memorias/memoryRAM.v"

module placement(out, clk, reset);
	input clk, reset;
	output reg out;
	parameter n0 = 4, n = n0*n0, n_edge = 15, n_node = 14, size_offset = 28;
	//Controles:
	reg reEA, reEB, reOX, reOY, rePX, rePY, reGrid;
	reg signed [32-1:0] addrEA, addrEB, addrOX, addrOY, addrPX, addrPY, addrGrid;
	wire signed [32-1:0] doutEA, doutEB, doutOX, doutOY, doutPX, doutPY, doutGrid;
	reg wePX, wePY, weGrid;
	reg signed [32-1:0] dinPX, dinPY, dinGrid;
	//Registradores:
	reg [16-1:0] state;
	reg [32-1:0] i, j, aux1, aux2, aux3, aux4;
	reg signed [32-1:0] pos_a_X, pos_a_Y, pos_b_X, pos_b_Y;
	reg signed [32-1:0] a, b;
	reg signed [32-1:0] xi, xj;
	reg signed [32-1:0] sum;
	reg signed [32-1:0] diff_pos_x, diff_pos_y;

	always @(posedge clk) begin
		if(reset) begin
			reEA <= 0; addrEA <= 0;
			reEB <= 0; addrEB <= 0;
			reOX <= 0; addrOX <= 0;
			reOY <= 0; addrOY <= 0;
			rePX <= 0; wePX <= 0; addrPX <= 0; dinPX <= 0;
			rePY <= 0; wePY <= 0; addrPY <= 0; dinPY <= 0;
			reGrid <= 0; weGrid <= 0; addrGrid <= 0; dinGrid <= 0;
			state <= 0;
			sum <= 0;
		end
		else begin
			case (state)
				0: begin //Inicializações
					$write("s 0\n");
					reEA <= 1; addrEA <= 0; a <= doutEA; //a = e_a[0]
					wePX <= 1; addrPX <= a; dinPX <= 0; //pos_X[a] = 0
					wePY <= 1; addrPY <= a; dinPY <= 0; //pos_Y[a] = 0
					state <= 1;
				end
				1: begin //Inicializações
					$write("s 1\n");
					rePX <= 1; addrPX <= 0; aux1 <= doutPX; //aux1 = pos_X[0] 
					rePY <= 1; addrPY <= 0; aux2 <= doutPY; //aux2 = pos_Y[0]
					i <= 0;
					j <= 0;
					state <= 11;
				end
				11: begin //Intro ao estado 2
					$write("s 11\n");
					aux3 = aux1*n+aux2; //pos_X[0] * n + pos_Y[0]
					weGrid <= 1; addrGrid <= aux3; dinGrid <= a; //grid[pos_X[0] * n + pos_Y[0]] = a
					state <= 2;
				end
				2: begin //Leitura das memórias
					$write("s 2\n");
					if(i == n_edge) begin
						i <= 0;
						state <= 8;
					end
					else begin
						reEA <= 1; addrEA <= i; a <= doutEA; //a = e_a[i]
						reEB <= 1; addrEB <= i; b <= doutEB; //b = e_b[i]
						state <= 16;
					end
				end
				16: begin //Leitura das memórias
					$write("s 16\n");
					rePX <= 1; addrPX <= a; pos_a_X <= doutPX; //pos_a_X <= pos_X[a]
					rePY <= 1; addrPY <= a; pos_a_Y <= doutPY; //pos_a_Y <= pos_Y[a]
					state <= 3;
				end
				3: begin //Leitura das memórias	
					$write("s 16\n");		
					rePX <= 1; addrPX <= b; pos_b_X <= doutPX; //pos_b_X = pos_X[b]
					rePY <= 1; addrPY <= b; pos_b_Y <= doutPY; //pos_b_Y = pos_Y[b]
					if(i==0) begin
						state <= 7;
					end
					else begin
						state <= 4;
					end
				end
				4: begin //Posição X de a
					$write("s4\n");
					if(pos_a_X != -1) begin
	          				state <= 7;
					 	j <= 0;
					end
					else begin
						rePX <= 1; addrPX <= i-1; aux1 <= doutPX; //aux1 = pos_X[i-1]
						reOX <= 1; addrOX <= j; aux2 <= doutOX; //aux2 = offset_x[j]
						rePY <= 1; addrPY <= i-1; aux3 <= doutPY; //aux3 = pos_Y[i-1]
						reOY <= 1; addrOY <= j; aux4 <= doutOY; //aux4 = offset_y[j]
						aux1 = aux1 + aux2; //pos_X[i-1] + offset_x[j]   //OBS: talvez precise de outro estado
						aux3 = aux3 + aux4; //pos_Y[i-1] + offset_y[j]
						state <= 5;
					end
				end
				5: begin //Posição x de a
					$write("s 5\n");
					wePX <= 1; addrPX <= a; dinPX <= aux1; //pos_X[a] = pos_X[i-1] + offset_x[j]
					wePY <= 1; addrPY <= a; dinPY <= aux3; //pos_Y[a] = pos_Y[i-1] + offset_y[j]
					state <= 12;
				end
				12: begin //Intro ao estado 6
					$write("s 12\n");
					rePX <= 1; addrPX <= a; xi <= doutPX; //xi = pos_X[a]
					rePY <= 1; addrPY <= a; xj <= doutPY; //xj = pos_Y[a]
					j++;
					aux1 = xi*n+xj;  //OBS: talvez pudesse ser criado outro estado, garantir que xi e xj foram atualizados antes
					reGrid <= 1; addrGrid <= aux1; aux2 <= doutGrid; //aux2 = grid[xi*n+j]
					state <= 6;
				end
				6: begin //Posição x de a
					$write("s 6\n");
					if(aux2 == -1 && xi < n && xi >= 0 && xj < n && xj >= 0) begin
						weGrid <= 1; addrGrid <= aux1; dinGrid <= a; //grid[xi*n+j] = a
						pos_a_X = xi;
						pos_a_Y = xj;
					end
					else if(j > size_offset) begin
						$display("No solution\n");
						out <= 0;
						state <= 10;
					end
					if(pos_a_X == -1) begin
						state = 4;
					end
					else begin
						state = 7;
						j=0;
					end
				end
				7://Posição X de b
				begin
					$write("s 7\n");
					if(pos_b_X != -1) begin
						state <= 11;
						j <= 0;
						i++;
					end
					else begin
						reOX <= 1; addrOX <= j; aux1 <= doutOX; //aux1 = offset_x[j]
						reOY <= 1; addrOY <= j; aux2 <= doutOY; //aux2 = offset_y[j]
						state <= 13;
					end
				end
				13: begin
					state <= 14;
					xi <= pos_a_X + aux1;
					xj <= pos_a_Y + aux2;
					aux1 = xi*n+xj; //talvez precise de um estado pra isso
				end
				14: begin 
					$write("s 13\n");
					j++;
					reGrid <= 1; addrGrid <= aux1; aux2 <= doutGrid; //aux2 = grid[xi*n+j]
					if(aux2 == -1 && xi < n && xi >= 0 && xj < n && xj >= 0) begin
						weGrid <= 1; addrGrid <= aux1; dinGrid <= b; //grid[xi*n+j] = b
						pos_b_X <= xi;
						pos_b_Y <= xj;
						wePX <= 1; addrPX <= b; dinPX <= xi; //pos_X[b] = xi
						wePY <= 1; addrPY <= b; dinPY <= xj; //pos_Y[b] = xj
						state <= 11;
						j <= 0;
						i++;
					end
					else if(pos_b_X == -1) begin
						state = 7;
					end
					else if(j > size_offset) begin
						$display("No solution\n");
						out <= 0;
						state <= 10;
					end
				end
				8://Evaluation
				begin
					$write("s 8\n");
					if(i == n_edge) begin
					 	state <= 10;
					end
					else begin
						reEA <= 1; addrEA <= i; a <= doutEA; //a = e_a[i]
						reEB <= 1; addrEB <= i; b <= doutEB; //b = e_b[i]
						state <= 17;
					end
				end
				17: begin
					$write("s 17\n");
					rePX <= 1; addrPX <= a; aux1 <= doutPX; //aux1 = pos_X[a]
					rePY <= 1; addrPY <= a; aux2 <= doutPY; //aux2 = pos_Y[a]
					state <= 15;
				end
				15: begin
					$write("s 15\n");
					rePX <= 1; addrPX <= b; aux3 <= doutPX; //aux3 = pos_X[b]
					rePY <= 1; addrPY <= b; aux4 <= doutPY; //aux4 = pos_Y[b]
					state <= 9;
				end
				9: begin //Evaluation
					$write("s 9\n");
					diff_pos_x = aux1-aux3;
					if(diff_pos_x < 0) begin
						diff_pos_x *= -1;
					end
					diff_pos_y = aux2-aux4;
					if(diff_pos_y < 0) begin
						diff_pos_y *= -1;
					end
					sum = diff_pos_x + diff_pos_y - 1;
					i++;
					state <= 8;
				end
				10: //display existe apenas na simulação
				begin
					$write("\nEvaluation = %1d\n", sum);
					out <= 1;
					$finish;
				end
			endcase
		end
	end
	memoryROM #(.init_file("dados/eaData.txt"), .data_depth(4)) ea (.clk(clk), .read(reEA), .addr(addrEA), .data(doutEA));
	memoryROM #(.init_file("dados/ebData.txt"), .data_depth(4)) eb (.clk(clk), .read(reEB), .addr(addrEB), .data(doutEB));
	memoryROM #(.init_file("dados/offsetXData.txt"), .data_depth(5)) offset_x (.clk(clk), .read(reOX), .addr(addrOX), .data(doutOX));
	memoryROM #(.init_file("dados/offsetYData.txt"), .data_depth(5)) offset_y (.clk(clk), .read(reOY), .addr(addrOY), .data(doutOY));
	memoryRAM #(.init_file("dados/posData.txt"), .data_depth(4)) pos_X (.clk(clk), .read(rePX), .write(wePX), .addr(addrPX), .dataRead(doutPX), .dataWrite(dinPX));
	memoryRAM #(.init_file("dados/posData.txt"), .data_depth(4)) pos_Y (.clk(clk), .read(rePY), .write(wePY), .addr(addrPY), .dataRead(doutPY), .dataWrite(dinPY));
	memoryRAM #(.init_file("dados/gridData.txt"), .data_depth(4)) grid (.clk(clk), .read(reGrid), .write(weGrid), .addr(addrGrid), .dataRead(doutGrid), .dataWrite(dinGrid));
endmodule

module test;
	reg clk;
	reg reset;
	initial begin
    $dumpfile("placement.vcd");
    $dumpvars(0, test);
		clk = 0;
		reset = 0;
		#1 reset = 1;
		#2 reset = 0;
	end
	always #1 clk = !clk;
	wire out;
	placement p1 (out, clk, reset);
endmodule

placement/verilog/placement.vcd
$date
	Fri Feb 14 10:56:52 2020
$end
$version
	Icarus Verilog
$end
$timescale
	1s
$end
$scope module test $end
$var wire 1 ! out $end
$var reg 1 " clk $end
$var reg 1 # reset $end
$scope module p1 $end
$var wire 1 " clk $end
$var wire 1 # reset $end
$var wire 32 $ doutPY [31:0] $end
$var wire 32 % doutPX [31:0] $end
$var wire 32 & doutOY [31:0] $end
$var wire 32 ' doutOX [31:0] $end
$var wire 32 ( doutGrid [31:0] $end
$var wire 32 ) doutEB [31:0] $end
$var wire 32 * doutEA [31:0] $end
$var reg 32 + a [31:0] $end
$var reg 32 , addrEA [31:0] $end
$var reg 32 - addrEB [31:0] $end
$var reg 32 . addrGrid [31:0] $end
$var reg 32 / addrOX [31:0] $end
$var reg 32 0 addrOY [31:0] $end
$var reg 32 1 addrPX [31:0] $end
$var reg 32 2 addrPY [31:0] $end
$var reg 32 3 aux1 [31:0] $end
$var reg 32 4 aux2 [31:0] $end
$var reg 32 5 aux3 [31:0] $end
$var reg 32 6 aux4 [31:0] $end
$var reg 32 7 b [31:0] $end
$var reg 32 8 diff_pos_x [31:0] $end
$var reg 32 9 diff_pos_y [31:0] $end
$var reg 32 : dinGrid [31:0] $end
$var reg 32 ; dinPX [31:0] $end
$var reg 32 < dinPY [31:0] $end
$var reg 32 = i [31:0] $end
$var reg 32 > j [31:0] $end
$var reg 1 ! out $end
$var reg 32 ? pos_a_X [31:0] $end
$var reg 32 @ pos_a_Y [31:0] $end
$var reg 32 A pos_b_X [31:0] $end
$var reg 32 B pos_b_Y [31:0] $end
$var reg 1 C reEA $end
$var reg 1 D reEB $end
$var reg 1 E reGrid $end
$var reg 1 F reOX $end
$var reg 1 G reOY $end
$var reg 1 H rePX $end
$var reg 1 I rePY $end
$var reg 16 J state [15:0] $end
$var reg 32 K sum [31:0] $end
$var reg 1 L weGrid $end
$var reg 1 M wePX $end
$var reg 1 N wePY $end
$var reg 32 O xi [31:0] $end
$var reg 32 P xj [31:0] $end
$scope module ea $end
$var wire 32 Q addr [31:0] $end
$var wire 1 " clk $end
$var wire 1 C read $end
$var reg 32 R data [31:0] $end
$upscope $end
$scope module eb $end
$var wire 32 S addr [31:0] $end
$var wire 1 " clk $end
$var wire 1 D read $end
$var reg 32 T data [31:0] $end
$upscope $end
$scope module grid $end
$var wire 32 U addr [31:0] $end
$var wire 1 " clk $end
$var wire 32 V dataWrite [31:0] $end
$var wire 1 E read $end
$var wire 1 L write $end
$var reg 32 W dataRead [31:0] $end
$upscope $end
$scope module offset_x $end
$var wire 32 X addr [31:0] $end
$var wire 1 " clk $end
$var wire 1 F read $end
$var reg 32 Y data [31:0] $end
$upscope $end
$scope module offset_y $end
$var wire 32 Z addr [31:0] $end
$var wire 1 " clk $end
$var wire 1 G read $end
$var reg 32 [ data [31:0] $end
$upscope $end
$scope module pos_X $end
$var wire 32 \ addr [31:0] $end
$var wire 1 " clk $end
$var wire 32 ] dataWrite [31:0] $end
$var wire 1 H read $end
$var wire 1 M write $end
$var reg 32 ^ dataRead [31:0] $end
$upscope $end
$scope module pos_Y $end
$var wire 32 _ addr [31:0] $end
$var wire 1 " clk $end
$var wire 32 ` dataWrite [31:0] $end
$var wire 1 I read $end
$var wire 1 N write $end
$var reg 32 a dataRead [31:0] $end
$upscope $end
$upscope $end
$upscope $end
$enddefinitions $end
#0
$dumpvars
b0 a
bx `
bx _
b0 ^
bx ]
bx \
b0 [
bx Z
b0 Y
bx X
b0 W
bx V
bx U
b0 T
bx S
b0 R
bx Q
bx P
bx O
xN
xM
xL
bx K
bx J
xI
xH
xG
xF
xE
xD
xC
bx B
bx A
bx @
bx ?
bx >
bx =
bx <
bx ;
bx :
bx 9
bx 8
bx 7
bx 6
bx 5
bx 4
bx 3
bx 2
bx 1
bx 0
bx /
bx .
bx -
bx ,
bx +
b0 *
b0 )
b0 (
b0 '
b0 &
b0 %
b0 $
0#
0"
x!
$end
#1
b0 K
b0 J
b0 :
b0 V
b0 .
b0 U
0L
0E
b0 <
b0 `
b0 2
b0 _
0N
0I
b0 ;
b0 ]
b0 1
b0 \
0M
0H
b0 0
b0 Z
0G
b0 /
b0 X
0F
b0 -
b0 S
0D
b0 ,
b0 Q
0C
1"
1#
#2
0"
#3
b1 J
bx 2
bx _
1N
bx 1
bx \
1M
b0 +
1C
1"
0#
#4
0"
#5
b1011 J
b0 >
b0 =
b0 4
b0 2
b0 _
1I
b0 3
b0 1
b0 \
1H
1"
#6
0"
#7
b10 J
1L
b11111111111111111111111111111111 $
b11111111111111111111111111111111 a
b11111111111111111111111111111111 %
b11111111111111111111111111111111 ^
b0 5
1"
#8
0"
#9
b0 %
b0 ^
b0 $
b0 a
b10000 J
b0 7
1D
1"
#10
0"
#11
b11 J
b0 @
b0 ?
b100 )
b100 T
1"
#12
0"
#13
b111 J
b0 B
b0 A
1"
#14
0"
#15
b1011 J
b1 =
1"
#16
0"
#17
b10 J
1"
#18
0"
#19
b10000 J
b100 7
b1 -
b1 S
b1 ,
b1 Q
1"
#20
0"
#21
b1 *
b1 R
b101 )
b101 T
b11 J
1"
#22
0"
#23
b100 J
b100 2
b100 _
b100 1
b100 \
1"
#24
0"
#25
b11111111111111111111111111111111 %
b11111111111111111111111111111111 ^
b11111111111111111111111111111111 $
b11111111111111111111111111111111 a
b111 J
1"
#26
0"
#27
b1011 J
b0 $
b0 a
b0 %
b0 ^
b10 =
1"
#28
0"
#29
b10 J
1"
#30
0"
#31
b10000 J
b101 7
b10 -
b10 S
b1 +
b10 ,
b10 Q
1"
#32
0"
#33
b10 *
b10 R
b110 )
b110 T
b11 J
b1 2
b1 _
b1 1
b1 \
1"
#34
0"
#35
b100 J
b101 2
b101 _
b101 1
b101 \
b11111111111111111111111111111111 $
b11111111111111111111111111111111 a
b11111111111111111111111111111111 %
b11111111111111111111111111111111 ^
1"
#36
0"
#37
b11111111111111111111111111111111 %
b11111111111111111111111111111111 ^
b11111111111111111111111111111111 $
b11111111111111111111111111111111 a
b111 J
1"
#38
0"
#39
b1011 J
b0 $
b0 a
b0 %
b0 ^
b11 =
1"
#40
0"
#41
b10 J
b1 :
b1 V
1"
#42
0"
#43
b10000 J
b110 7
b11 -
b11 S
b10 +
b11 ,
b11 Q
1"
#44
0"
#45
b11 *
b11 R
b111 )
b111 T
b11 J
b10 2
b10 _
b10 1
b10 \
1"
#46
0"
#47
b100 J
b110 2
b110 _
b110 1
b110 \
b11111111111111111111111111111111 $
b11111111111111111111111111111111 a
b11111111111111111111111111111111 %
b11111111111111111111111111111111 ^
1"
#48
0"
#49
b11111111111111111111111111111111 %
b11111111111111111111111111111111 ^
b11111111111111111111111111111111 $
b11111111111111111111111111111111 a
b111 J
1"
#50
0"
#51
b1011 J
b0 $
b0 a
b0 %
b0 ^
b100 =
1"
#52
0"
#53
b10 J
b10 :
b10 V
1"
#54
0"
#55
b10000 J
b111 7
b100 -
b100 S
b11 +
b100 ,
b100 Q
1"
#56
0"
#57
b100 *
b100 R
b1000 )
b1000 T
b11 J
b11 2
b11 _
b11 1
b11 \
1"
#58
0"
#59
b100 J
b111 2
b111 _
b111 1
b111 \
b11111111111111111111111111111111 $
b11111111111111111111111111111111 a
b11111111111111111111111111111111 %
b11111111111111111111111111111111 ^
1"
#60
0"
#61
b11111111111111111111111111111111 %
b11111111111111111111111111111111 ^
b11111111111111111111111111111111 $
b11111111111111111111111111111111 a
b111 J
1"
#62
0"
#63
b1011 J
b0 $
b0 a
b0 %
b0 ^
b101 =
1"
#64
0"
#65
b10 J
b11 :
b11 V
1"
#66
0"
#67
b10000 J
b1000 7
b101 -
b101 S
b100 +
b101 ,
b101 Q
1"
#68
0"
#69
b101 *
b101 R
b1001 )
b1001 T
b11 J
b100 2
b100 _
b100 1
b100 \
1"
#70
0"
#71
b100 J
b1000 2
b1000 _
b1000 1
b1000 \
1"
#72
0"
#73
b11111111111111111111111111111111 %
b11111111111111111111111111111111 ^
b11111111111111111111111111111111 $
b11111111111111111111111111111111 a
b111 J
1"
#74
0"
#75
b1011 J
b0 $
b0 a
b0 %
b0 ^
b110 =
1"
#76
0"
#77
b10 J
b100 :
b100 V
1"
#78
0"
#79
b10000 J
b1001 7
b110 -
b110 S
b101 +
b110 ,
b110 Q
1"
#80
0"
#81
b110 *
b110 R
b1010 )
b1010 T
b11 J
b101 2
b101 _
b101 1
b101 \
1"
#82
0"
#83
b100 J
b1001 2
b1001 _
b1001 1
b1001 \
1"
#84
0"
#85
b11111111111111111111111111111111 %
b11111111111111111111111111111111 ^
b11111111111111111111111111111111 $
b11111111111111111111111111111111 a
b111 J
1"
#86
0"
#87
b1011 J
b0 $
b0 a
b0 %
b0 ^
b111 =
1"
#88
0"
#89
b10 J
b101 :
b101 V
1"
#90
0"
#91
b10000 J
b1010 7
b111 -
b111 S
b110 +
b111 ,
b111 Q
1"
#92
0"
#93
b111 *
b111 R
b100 )
b100 T
b11 J
b110 2
b110 _
b110 1
b110 \
1"
#94
0"
#95
b100 J
b1010 2
b1010 _
b1010 1
b1010 \
1"
#96
0"
#97
b11111111111111111111111111111111 %
b11111111111111111111111111111111 ^
b11111111111111111111111111111111 $
b11111111111111111111111111111111 a
b111 J
1"
#98
0"
#99
b1011 J
b0 $
b0 a
b0 %
b0 ^
b1000 =
1"
#100
0"
#101
b10 J
b110 :
b110 V
1"
#102
0"
#103
b10000 J
b100 7
b1000 -
b1000 S
b111 +
b1000 ,
b1000 Q
1"
#104
0"
#105
b101 )
b101 T
b11 J
b111 2
b111 _
b111 1
b111 \
1"
#106
0"
#107
b100 J
b100 2
b100 _
b100 1
b100 \
1"
#108
0"
#109
b111 J
1"
#110
0"
#111
b1011 J
b1001 =
1"
#112
0"
#113
b10 J
b111 :
b111 V
1"
#114
0"
#115
b10000 J
b101 7
b1001 -
b1001 S
b1001 ,
b1001 Q
1"
#116
0"
#117
b110 )
b110 T
b11 J
b111 2
b111 _
b111 1
b111 \
1"
#118
0"
#119
b100 J
b101 2
b101 _
b101 1
b101 \
1"
#120
0"
#121
b111 J
1"
#122
0"
#123
b1011 J
b1010 =
1"
#124
0"
#125
b10 J
1"
#126
0"
#127
b10000 J
b110 7
b1010 -
b1010 S
b1010 ,
b1010 Q
1"
#128
0"
#129
b1000 *
b1000 R
b1011 )
b1011 T
b11 J
b111 2
b111 _
b111 1
b111 \
1"
#130
0"
#131
b100 J
b110 2
b110 _
b110 1
b110 \
1"
#132
0"
#133
b111 J
1"
#134
0"
#135
b1011 J
b1011 =
1"
#136
0"
#137
b10 J
1"
#138
0"
#139
b10000 J
b1011 7
b1011 -
b1011 S
b1000 +
b1011 ,
b1011 Q
1"
#140
0"
#141
b1001 *
b1001 R
b11 J
b1000 2
b1000 _
b1000 1
b1000 \
1"
#142
0"
#143
b100 J
b1011 2
b1011 _
b1011 1
b1011 \
1"
#144
0"
#145
b11111111111111111111111111111111 %
b11111111111111111111111111111111 ^
b11111111111111111111111111111111 $
b11111111111111111111111111111111 a
b111 J
1"
#146
0"
#147
b1011 J
b0 $
b0 a
b0 %
b0 ^
b1100 =
1"
#148
0"
#149
b10 J
b1000 :
b1000 V
1"
#150
0"
#151
b10000 J
b1100 -
b1100 S
b1001 +
b1100 ,
b1100 Q
1"
#152
0"
#153
b1010 *
b1010 R
b1100 )
b1100 T
b11 J
b1001 2
b1001 _
b1001 1
b1001 \
1"
#154
0"
#155
b100 J
b1011 2
b1011 _
b1011 1
b1011 \
1"
#156
0"
#157
b111 J
1"
#158
0"
#159
b1011 J
b1101 =
1"
#160
0"
#161
b10 J
b1001 :
b1001 V
1"
#162
0"
#163
b10000 J
b1100 7
b1101 -
b1101 S
b1010 +
b1101 ,
b1101 Q
1"
#164
0"
#165
b1011 *
b1011 R
b1101 )
b1101 T
b11 J
b1010 2
b1010 _
b1010 1
b1010 \
1"
#166
0"
#167
b100 J
b1100 2
b1100 _
b1100 1
b1100 \
1"
#168
0"
#169
b11111111111111111111111111111111 %
b11111111111111111111111111111111 ^
b11111111111111111111111111111111 $
b11111111111111111111111111111111 a
b111 J
1"
#170
0"
#171
b1011 J
b0 $
b0 a
b0 %
b0 ^
b1110 =
1"
#172
0"
#173
b10 J
b1010 :
b1010 V
1"
#174
0"
#175
b10000 J
b1101 7
b1110 -
b1110 S
b1011 +
b1110 ,
b1110 Q
1"
#176
0"
#177
b1100 *
b1100 R
b11 J
b1011 2
b1011 _
b1011 1
b1011 \
1"
#178
0"
#179
b100 J
b1101 2
b1101 _
b1101 1
b1101 \
1"
#180
0"
#181
b11111111111111111111111111111111 %
b11111111111111111111111111111111 ^
b11111111111111111111111111111111 $
b11111111111111111111111111111111 a
b111 J
1"
#182
0"
#183
b1011 J
b0 $
b0 a
b0 %
b0 ^
b1111 =
1"
#184
0"
#185
b10 J
b1011 :
b1011 V
1"
#186
0"
#187
b1000 J
b0 =
1"
#188
0"
#189
b10001 J
b0 -
b0 S
b1100 +
b0 ,
b0 Q
1"
#190
0"
#191
b1111 J
b1100 2
b1100 _
b1100 1
b1100 \
b100 )
b100 T
b0 *
b0 R
1"
#192
0"
#193
b1001 J
b0 6
b1101 2
b1101 _
b1101 1
b1101 \
1"
#194
0"
#195
b1000 J
b1 =
b11111111111111111111111111111111 K
b0 9
b0 8
1"
#196
0"
#197
b10001 J
b100 7
b1 -
b1 S
b0 +
b1 ,
b1 Q
1"
#198
0"
#199
b1111 J
b0 2
b0 _
b0 1
b0 \
b101 )
b101 T
b1 *
b1 R
1"
#200
0"
#201
b1001 J
b100 2
b100 _
b100 1
b100 \
1"
#202
0"
#203
b1000 J
b10 =
1"
#204
0"
#205
b10001 J
b101 7
b10 -
b10 S
b1 +
b10 ,
b10 Q
1"
#206
0"
#207
b1111 J
b1 2
b1 _
b1 1
b1 \
b110 )
b110 T
b10 *
b10 R
1"
#208
0"
#209
b1001 J
b101 2
b101 _
b101 1
b101 \
1"
#210
0"
#211
b1000 J
b11 =
1"
#212
0"
#213
b10001 J
b110 7
b11 -
b11 S
b10 +
b11 ,
b11 Q
1"
#214
0"
#215
b1111 J
b10 2
b10 _
b10 1
b10 \
b111 )
b111 T
b11 *
b11 R
1"
#216
0"
#217
b1001 J
b110 2
b110 _
b110 1
b110 \
1"
#218
0"
#219
b1000 J
b100 =
1"
#220
0"
#221
b10001 J
b111 7
b100 -
b100 S
b11 +
b100 ,
b100 Q
1"
#222
0"
#223
b1111 J
b11 2
b11 _
b11 1
b11 \
b1000 )
b1000 T
b100 *
b100 R
1"
#224
0"
#225
b1001 J
b111 2
b111 _
b111 1
b111 \
1"
#226
0"
#227
b1000 J
b101 =
1"
#228
0"
#229
b10001 J
b1000 7
b101 -
b101 S
b100 +
b101 ,
b101 Q
1"
#230
0"
#231
b1111 J
b100 2
b100 _
b100 1
b100 \
b1001 )
b1001 T
b101 *
b101 R
1"
#232
0"
#233
b1001 J
b1000 2
b1000 _
b1000 1
b1000 \
1"
#234
0"
#235
b1000 J
b110 =
1"
#236
0"
#237
b10001 J
b1001 7
b110 -
b110 S
b101 +
b110 ,
b110 Q
1"
#238
0"
#239
b1111 J
b101 2
b101 _
b101 1
b101 \
b1010 )
b1010 T
b110 *
b110 R
1"
#240
0"
#241
b1001 J
b1001 2
b1001 _
b1001 1
b1001 \
1"
#242
0"
#243
b1000 J
b111 =
1"
#244
0"
#245
b10001 J
b1010 7
b111 -
b111 S
b110 +
b111 ,
b111 Q
1"
#246
0"
#247
b1111 J
b110 2
b110 _
b110 1
b110 \
b100 )
b100 T
b111 *
b111 R
1"
#248
0"
#249
b1001 J
b1010 2
b1010 _
b1010 1
b1010 \
1"
#250
0"
#251
b1000 J
b1000 =
1"
#252
0"
#253
b10001 J
b100 7
b1000 -
b1000 S
b111 +
b1000 ,
b1000 Q
1"
#254
0"
#255
b1111 J
b111 2
b111 _
b111 1
b111 \
b101 )
b101 T
1"
#256
0"
#257
b1001 J
b100 2
b100 _
b100 1
b100 \
1"
#258
0"
#259
b1000 J
b1001 =
1"
#260
0"
#261
b10001 J
b101 7
b1001 -
b1001 S
b1001 ,
b1001 Q
1"
#262
0"
#263
b1111 J
b111 2
b111 _
b111 1
b111 \
b110 )
b110 T
1"
#264
0"
#265
b1001 J
b101 2
b101 _
b101 1
b101 \
1"
#266
0"
#267
b1000 J
b1010 =
1"
#268
0"
#269
b10001 J
b110 7
b1010 -
b1010 S
b1010 ,
b1010 Q
1"
#270
0"
#271
b1111 J
b111 2
b111 _
b111 1
b111 \
b1011 )
b1011 T
b1000 *
b1000 R
1"
#272
0"
#273
b1001 J
b110 2
b110 _
b110 1
b110 \
1"
#274
0"
#275
b1000 J
b1011 =
1"
#276
0"
#277
b10001 J
b1011 7
b1011 -
b1011 S
b1000 +
b1011 ,
b1011 Q
1"
#278
0"
#279
b1111 J
b1000 2
b1000 _
b1000 1
b1000 \
b1001 *
b1001 R
1"
#280
0"
#281
b1001 J
b1011 2
b1011 _
b1011 1
b1011 \
1"
#282
0"
#283
b1000 J
b1100 =
1"
#284
0"
#285
b10001 J
b1100 -
b1100 S
b1001 +
b1100 ,
b1100 Q
1"
#286
0"
#287
b1111 J
b1001 2
b1001 _
b1001 1
b1001 \
b1100 )
b1100 T
b1010 *
b1010 R
1"
#288
0"
#289
b1001 J
b1011 2
b1011 _
b1011 1
b1011 \
1"
#290
0"
#291
b1000 J
b1101 =
1"
#292
0"
#293
b10001 J
b1100 7
b1101 -
b1101 S
b1010 +
b1101 ,
b1101 Q
1"
#294
0"
#295
b1111 J
b1010 2
b1010 _
b1010 1
b1010 \
b1101 )
b1101 T
b1011 *
b1011 R
1"
#296
0"
#297
b1001 J
b1100 2
b1100 _
b1100 1
b1100 \
1"
#298
0"
#299
b1000 J
b1110 =
1"
#300
0"
#301
b10001 J
b1101 7
b1110 -
b1110 S
b1011 +
b1110 ,
b1110 Q
1"
#302
0"
#303
b1111 J
b1011 2
b1011 _
b1011 1
b1011 \
b1100 *
b1100 R
1"
#304
0"
#305
b1001 J
b1101 2
b1101 _
b1101 1
b1101 \
1"
#306
0"
#307
b1000 J
b1111 =
1"
#308
0"
#309
b1010 J
1"
#310
0"
#311
1!
1"
