placement/1hop_resultados/memorias/memoryRAM.v
module memoryRAM #(
  parameter init_file = "mem_file.txt",
  parameter data_depth = 4
  )(clk, reset, read, write, addr, dataRead, dataWrite);
  input clk, reset, read, write;
  input signed [32-1:0] addr, dataWrite;
  output reg signed [32-1:0] dataRead;
  reg signed [32-1:0] memRAM [(2**data_depth)-1:0];
  reg [32-1:0] i, j;
  always @ (posedge clk) begin
	if(reset) begin
		dataRead = 0;
    		$readmemh(init_file, memRAM, 0, (2**data_depth)-1);
	end
	else begin
	    dataRead <= 0;
	    if(read) begin
	      dataRead <= memRAM[addr];
	    end
	    if(write) begin
	      memRAM[addr] <= dataWrite;
	    end
	    /*$display();
	    for(i=0; i<data_depth; i++) begin
		for(j=0; j<data_depth; j++) begin
		    $write("%4d", $signed(memRAM[i*data_depth+j]));
		end
		$display();
	    end*/
	end
  end
endmodule

placement/1hop_resultados/memorias/memoryROM.v
module memoryROM #(
  parameter init_file = "mem_file.txt",
  parameter data_depth = 5
  )(clk, reset, read, addr, data);
  input clk, reset, read;
  input signed [32-1:0] addr;
  output reg signed [32-1:0] data;
  reg signed [32-1:0] memROM [(2**data_depth)-1:0];
  always @ (posedge clk) begin
    if(reset) begin
	data = 0;
        $readmemh(init_file, memROM, 0, (2**data_depth)-1);
    end
    else begin
        if(read) begin
            data <= memROM[addr];
        end
    end
  end
endmodule

placement/1hop_resultados/placement_1hop_ewf.v
`include "memorias/memoryRAM.v"
`include "memorias/memoryROM.v"

module placement(out, clk, reset);
	//Parameters of states:
	parameter v = 11;
	parameter init0 = 0, init1 = 1, init2 = 2, init3 = 3;
	parameter reMem0 = 4, reMem1 = 5, reMem2 = 6, reMem3 = 7, reMem4 = 8;
	parameter posA0 = 9, posA1 = 10, posA2 = 11, posA3 = 12, posA4 = 13, posA5 = 14, posA6 = 15, posA7 = 16;
	parameter posB0 = 17, posB1 = 18, posB2 = 19, posB3 = 20, posB4 = 21, posB5 = 22;
	parameter eval0 = 23, eval1 = 24, eval2 = 25, eval3 = 26, eval4 = 27, eval5 = 28, eval6 = 29, eval7 = 30;
	parameter exit = 31, waitState = 32;
	//Parameters of datas:
	parameter n = 9, n_edge = 79, size_offset = 63, tam_ex_mem = 4, tam_off_mem = 5, tam_pos_mem = 4;
	//Inputs and output:
	input clk, reset;
	output reg out;
	//Controls:
	reg reEA, reEB, reOX, reOY, rePX, rePY, reGrid;
	reg signed [32-1:0] addrEA, addrEB, addrOX, addrOY, addrPX, addrPY, addrGrid;
	wire signed [32-1:0] doutEA, doutEB, doutOX, doutOY, doutPX, doutPY, doutGrid;
	reg wePX, wePY, weGrid;
	reg signed [32-1:0] dinPX, dinPY, dinGrid;
	wire [32-1:0] outPX, outPY, outOX, outOY, outGrid;
	//Regs and wires:
	reg [32-1:0] state, next_state, i, j;
	reg [32-1:0] aux1, aux2, aux3, aux4;
	reg signed [32-1:0] pos_a_X, pos_a_Y, pos_b_X, pos_b_Y;
	wire signed [32-1:0] a, b;
	reg signed [32-1:0] xi, xj;
	reg signed [32-1:0] sum, sum_1hop;
	reg signed [32-1:0] diff_pos_x, diff_pos_y;
	reg [32-1:0] cont;
	//Outputs of memories:
	assign a = doutEA;
	assign b = doutEB;
	assign outPX = doutPX;
	assign outPY = doutPY;
	assign outOX = doutOX;
	assign outOY = doutOY;
	assign outGrid = doutGrid;

	/*
	States [0,3]: Initialization;
	States [4,8]: Read of memories;
	States [9,16]: Position X of A;
	States [17,22]: Position X of B;
	States [23,30]: Evaluation;
	State 31: End;
	OBS.: States 32 = Wait state.
	*/

	always @(posedge clk) begin
		if(reset) begin
			reEA <= 0; addrEA <= 0;
			reEB <= 0; addrEB <= 0;
			reOX <= 0; addrOX <= 0;
			reOY <= 0; addrOY <= 0;
			rePX <= 0; wePX <= 0; addrPX <= 0; dinPX <= 0;
			rePY <= 0; wePY <= 0; addrPY <= 0; dinPY <= 0;
			reGrid <= 0; weGrid <= 0; addrGrid <= 0; dinGrid <= 0;
			state <= 0; next_state <= 0;
			sum <= 0; cont <= 0; sum_1hop <= 0;
		end
		else begin
			cont <= cont + 1;
			reEA <= 0; reEB <= 0;
			reOX <= 0; reOY <= 0;
			rePX <= 0; wePX <= 0;
			rePY <= 0; wePY <= 0;
			reGrid <= 0; weGrid <= 0;
			//State machine:
			case (state)
				init0: begin
					reEA <= 1; addrEA <= 0;
					reOX <= 1; addrOX <= 62; //le primeiro valor offsetX
					reOY <= 1; addrOY <= 62; //le primeiro valor offsetY
					//state <= init1;
					state <= waitState;
					next_state <= init1;
				end
				init1: begin
					//$display("OFFSET Y ",outOY);
					if(outOY >= 0) begin						
						wePY <= 1; addrPY <= a; dinPY <= outOY;
					end else begin
						wePY <= 1; addrPY <= a; dinPY <= (outOY ^ (32'b11111111111111111111111111111111)) + 1;
					end

					if(outOX >= 0)begin
						wePX <= 1; addrPX <= a; dinPX <= outOX;
					end else begin
						wePX <= 1; addrPX <= a; dinPX <= (outOX ^ (32'b11111111111111111111111111111111)) + 1;
					end
					state <= init2;
				end
				init2: begin
					rePX <= 1; addrPX <= a;
					rePY <= 1; addrPY <= a;
					i <= 0;
					j <= 0;
					state <= waitState;
					next_state <= init3;
				end
				init3: begin
					weGrid <= 1; addrGrid <= outPX*n+outPY; dinGrid <= a;
					state <= reMem0;
				end
				reMem0: begin
					if(i == n_edge) begin
						i <= 0;
						state <= eval0;
					end
					else begin
						reEA <= 1; addrEA <= i;
						reEB <= 1; addrEB <= i;
						state <= waitState;
						next_state <= reMem1;
					end
				end
				reMem1: begin
					rePX <= 1; addrPX <= a;
					rePY <= 1; addrPY <= a;
					state <= waitState;
					next_state <= reMem2;
				end
				reMem2: begin
					pos_a_X <= outPX;
					pos_a_Y <= outPY;
					state <= reMem3;
					next_state <= reMem4;
				end
				reMem3: begin
					rePX <= 1; addrPX <= b;
					rePY <= 1; addrPY <= b;
					state <= waitState;
				end
				reMem4: begin
					pos_b_X <= outPX;
					pos_b_Y <= outPY;
					if(i==0) begin
						state <= posB0;
					end
					else begin
						state <= posA0;
					end
				end
				posA0: begin
					if(pos_a_X != -1) begin
	          state <= posB0;
				 		j <= 0;
			  		end
					else begin
						rePX <= 1; addrPX <= i-1;
						reOX <= 1; addrOX <= j;
						rePY <= 1; addrPY <= i-1;
						reOY <= 1; addrOY <= j;
						state <= waitState;
						next_state <= posA1;
					end
				end
				posA1: begin
					aux1 <= outPX + outOX;
					aux3 <= outPY + outOY;
					state <= posA2;
				end
				posA2: begin
					wePX <= 1; addrPX <= a; dinPX <= aux1;
					wePY <= 1; addrPY <= a; dinPY <= aux3;
					state <= posA3;
				end
				posA3: begin
					rePX <= 1; addrPX <= a;
					rePY <= 1; addrPY <= a;
					j++;
					state <= waitState;
					next_state <= posA4;
				end
				posA4: begin
					xi <= outPX;
					xj <= outPY;
					aux1 <= outPX*n+outPY;
					state <= posA5;
				end
				posA5: begin
					reGrid <= 1; addrGrid <= aux1;
					state <= waitState;
					next_state <= posA6;
				end
				posA6: begin
					aux2 <= outGrid;
					state <= posA7;
				end
				posA7: begin
					if(aux2 == -1 && xi < n && xi >= 0 && xj < n && xj >= 0) begin
						weGrid <= 1; addrGrid <= aux1; dinGrid <= a;
						pos_a_X <= xi;
						pos_a_Y <= xj;
						state <= posB0;
						j <= 0;
					end
					else if(pos_a_X == -1) begin
						state <= posA0;
					end
					if(j > size_offset) begin
						$display("No solution\n");
						out <= 0;
						state <= exit;
					end
				end
				posB0: begin
					if(pos_b_X != -1) begin
						state <= reMem0;
						j <= 0;
						i++;
					end
					else begin
						reOX <= 1; addrOX <= j;
						reOY <= 1; addrOY <= j;
						state <= waitState;
						next_state <= posB1;
					end
				end
				posB1: begin
					xi <= pos_a_X + outOX;
					xj <= pos_a_Y + outOY;
					state <= posB2;
				end
				posB2: begin
					aux1 <= xi*n+xj;
					state <= posB3;
				end
				posB3: begin
					j++;
					reGrid <= 1; addrGrid <= aux1;
					state <= waitState;
					next_state <= posB4;
				end
				posB4: begin
					aux2 <= outGrid;
					state <= posB5;
				end
				posB5: begin
					if(aux2 == -1 && xi < n && xi >= 0 && xj < n && xj >= 0) begin
						weGrid <= 1; addrGrid <= aux1; dinGrid <= b;
						pos_b_X <= xi;
						pos_b_Y <= xj;
						wePX <= 1; addrPX <= b; dinPX <= xi;
						wePY <= 1; addrPY <= b; dinPY <= xj;
						j <= 0;
						i++;
						state <= reMem0;
					end
					else if(pos_b_X == -1) begin
						state <= posB0;
					end
					if(j > size_offset) begin
						$display("No solution\n");
						out <= 0;
						state <= exit;
					end
				end
				eval0: begin
					if(i == n_edge) begin
					 	state <= exit;
					end
					else begin
						reEA <= 1; addrEA <= i;
						reEB <= 1; addrEB <= i;
						state <= waitState;
						next_state <= eval1;
					end
				end
				eval1: begin
					rePX <= 1; addrPX <= a;
					rePY <= 1; addrPY <= a;
					state <= waitState;
					next_state <= eval2;
				end
				eval2: begin
					aux1 <= outPX;
					aux2 <= outPY;
					state <= reMem3;
					next_state <= eval3;
				end
				eval3: begin
					aux3 <= outPX;
					aux4 <= outPY;
					state <= eval4;
				end
				eval4: begin
					diff_pos_x <= aux1 - aux3;
					state <= eval5;
				end
				eval5: begin
					if(diff_pos_x < 0) begin
						diff_pos_x <= (diff_pos_x ^ (32'b11111111111111111111111111111111)) + 1;
					end
					diff_pos_y <= aux2 - aux4;
					state <= eval6;
				end
				eval6: begin
					if(diff_pos_y < 0) begin
						diff_pos_y <= (diff_pos_y ^ (32'b11111111111111111111111111111111)) + 1;
					end
					state <= eval7;
				end
				eval7: begin
					sum <= sum + diff_pos_x + diff_pos_y - 1;
					sum_1hop <= sum_1hop + ((diff_pos_x >> 1) + diff_pos_x[0]) + ((diff_pos_y >> 1) + diff_pos_y[0]) - 1;
					i++;
					state <= eval0;
				end
				exit: begin
					out <= 1;
					$write("\nEvaluation = %1d\nEvaluation 1-hop = %1d\nCycles = %1d\n", sum, sum_1hop, cont);
					$finish;
				end
				waitState: begin
					state <= next_state;
				end
			endcase
		end
	end
	memoryROM #(.init_file("dados/benchmarks/ewf/eaData.txt"), .data_depth(v)) ea (.clk(clk), .reset(reset), .read(reEA), .addr(addrEA), .data(doutEA));
	memoryROM #(.init_file("dados/benchmarks/ewf/ebData.txt"), .data_depth(v)) eb (.clk(clk), .reset(reset), .read(reEB), .addr(addrEB), .data(doutEB));
	memoryROM #(.init_file("offsetXData.txt"), .data_depth(6)) offset_x (.clk(clk), .reset(reset), .read(reOX), .addr(addrOX), .data(doutOX));
	memoryROM #(.init_file("offsetYData.txt"), .data_depth(6)) offset_y (.clk(clk), .reset(reset), .read(reOY), .addr(addrOY), .data(doutOY));
	memoryRAM #(.init_file("dados/benchmarks/ewf/posData.txt"), .data_depth(v)) pos_X (.clk(clk), .reset(reset), .read(rePX), .write(wePX), .addr(addrPX), .dataRead(doutPX), .dataWrite(dinPX));
	memoryRAM #(.init_file("dados/benchmarks/ewf/posData.txt"), .data_depth(v)) pos_Y (.clk(clk), .reset(reset), .read(rePY), .write(wePY), .addr(addrPY), .dataRead(doutPY), .dataWrite(dinPY));
	memoryRAM #(.init_file("dados/gridData.txt"), .data_depth(n)) grid (.clk(clk), .reset(reset), .read(reGrid), .write(weGrid), .addr(addrGrid), .dataRead(doutGrid), .dataWrite(dinGrid));

endmodule

module test;
	reg clk;
	reg reset;
	initial begin
		$dumpfile("placement_1hop.vcd");
		$dumpvars;
		clk = 0;
		reset = 0;
		#1 reset = 1;
		#2 reset = 0;
	end
	always #1 clk = !clk;
	wire out;
	placement p1 (out, clk, reset);
endmodule

placement/1hop_resultados/placement_1hop.vcd
$date
	Mon Mar 23 23:13:29 2020
$end
$version
	Icarus Verilog
$end
$timescale
	1s
$end
$scope module test $end
$var wire 1 ! out $end
$var reg 1 " clk $end
$var reg 1 # reset $end
$scope module p1 $end
$var wire 32 $ a [31:0] $end
$var wire 32 % b [31:0] $end
$var wire 1 " clk $end
$var wire 32 & outGrid [31:0] $end
$var wire 32 ' outOX [31:0] $end
$var wire 32 ( outOY [31:0] $end
$var wire 32 ) outPX [31:0] $end
$var wire 32 * outPY [31:0] $end
$var wire 1 # reset $end
$var wire 32 + doutPY [31:0] $end
$var wire 32 , doutPX [31:0] $end
$var wire 32 - doutOY [31:0] $end
$var wire 32 . doutOX [31:0] $end
$var wire 32 / doutGrid [31:0] $end
$var wire 32 0 doutEB [31:0] $end
$var wire 32 1 doutEA [31:0] $end
$var reg 32 2 addrEA [31:0] $end
$var reg 32 3 addrEB [31:0] $end
$var reg 32 4 addrGrid [31:0] $end
$var reg 32 5 addrOX [31:0] $end
$var reg 32 6 addrOY [31:0] $end
$var reg 32 7 addrPX [31:0] $end
$var reg 32 8 addrPY [31:0] $end
$var reg 32 9 aux1 [31:0] $end
$var reg 32 : aux2 [31:0] $end
$var reg 32 ; aux3 [31:0] $end
$var reg 32 < aux4 [31:0] $end
$var reg 32 = cont [31:0] $end
$var reg 32 > diff_pos_x [31:0] $end
$var reg 32 ? diff_pos_y [31:0] $end
$var reg 32 @ dinGrid [31:0] $end
$var reg 32 A dinPX [31:0] $end
$var reg 32 B dinPY [31:0] $end
$var reg 32 C i [31:0] $end
$var reg 32 D j [31:0] $end
$var reg 32 E next_state [31:0] $end
$var reg 1 ! out $end
$var reg 32 F pos_a_X [31:0] $end
$var reg 32 G pos_a_Y [31:0] $end
$var reg 32 H pos_b_X [31:0] $end
$var reg 32 I pos_b_Y [31:0] $end
$var reg 1 J reEA $end
$var reg 1 K reEB $end
$var reg 1 L reGrid $end
$var reg 1 M reOX $end
$var reg 1 N reOY $end
$var reg 1 O rePX $end
$var reg 1 P rePY $end
$var reg 32 Q state [31:0] $end
$var reg 32 R sum [31:0] $end
$var reg 32 S sum_1hop [31:0] $end
$var reg 1 T weGrid $end
$var reg 1 U wePX $end
$var reg 1 V wePY $end
$var reg 32 W xi [31:0] $end
$var reg 32 X xj [31:0] $end
$scope module ea $end
$var wire 32 Y addr [31:0] $end
$var wire 1 " clk $end
$var wire 1 J read $end
$var wire 1 # reset $end
$var reg 32 Z data [31:0] $end
$upscope $end
$scope module eb $end
$var wire 32 [ addr [31:0] $end
$var wire 1 " clk $end
$var wire 1 K read $end
$var wire 1 # reset $end
$var reg 32 \ data [31:0] $end
$upscope $end
$scope module grid $end
$var wire 32 ] addr [31:0] $end
$var wire 1 " clk $end
$var wire 32 ^ dataWrite [31:0] $end
$var wire 1 L read $end
$var wire 1 # reset $end
$var wire 1 T write $end
$var reg 32 _ dataRead [31:0] $end
$upscope $end
$scope module offset_x $end
$var wire 32 ` addr [31:0] $end
$var wire 1 " clk $end
$var wire 1 M read $end
$var wire 1 # reset $end
$var reg 32 a data [31:0] $end
$upscope $end
$scope module offset_y $end
$var wire 32 b addr [31:0] $end
$var wire 1 " clk $end
$var wire 1 N read $end
$var wire 1 # reset $end
$var reg 32 c data [31:0] $end
$upscope $end
$scope module pos_X $end
$var wire 32 d addr [31:0] $end
$var wire 1 " clk $end
$var wire 32 e dataWrite [31:0] $end
$var wire 1 O read $end
$var wire 1 # reset $end
$var wire 1 U write $end
$var reg 32 f dataRead [31:0] $end
$upscope $end
$scope module pos_Y $end
$var wire 32 g addr [31:0] $end
$var wire 1 " clk $end
$var wire 32 h dataWrite [31:0] $end
$var wire 1 P read $end
$var wire 1 # reset $end
$var wire 1 V write $end
$var reg 32 i dataRead [31:0] $end
$upscope $end
$upscope $end
$upscope $end
$enddefinitions $end
#0
$dumpvars
bx i
bx h
bx g
bx f
bx e
bx d
bx c
bx b
bx a
bx `
bx _
bx ^
bx ]
bx \
bx [
bx Z
bx Y
bx X
bx W
xV
xU
xT
bx S
bx R
bx Q
xP
xO
xN
xM
xL
xK
xJ
bx I
bx H
bx G
bx F
bx E
bx D
bx C
bx B
bx A
bx @
bx ?
bx >
bx =
bx <
bx ;
bx :
bx 9
bx 8
bx 7
bx 6
bx 5
bx 4
bx 3
bx 2
bx 1
bx 0
bx /
bx .
bx -
bx ,
bx +
bx *
bx )
bx (
bx '
bx &
bx %
bx $
0#
0"
x!
$end
#1
b0 S
b0 =
b0 R
b0 E
b0 Q
b0 @
b0 ^
b0 4
b0 ]
0T
0L
b0 B
b0 h
b0 8
b0 g
0V
0P
b0 A
b0 e
b0 7
b0 d
0U
0O
b0 6
b0 b
0N
b0 5
b0 `
0M
b0 3
b0 [
0K
b0 2
b0 Y
0J
b0 $
b0 1
b0 Z
b0 %
b0 0
b0 \
b0 '
b0 .
b0 a
b0 (
b0 -
b0 c
b0 )
b0 ,
b0 f
b0 *
b0 +
b0 i
b0 &
b0 /
b0 _
1"
1#
#2
0"
#3
b1 E
b100000 Q
b111110 6
b111110 b
1N
b111110 5
b111110 `
1M
1J
b1 =
1"
0#
#4
0"
#5
b1 Q
0N
0M
0J
b10 =
1"
#6
0"
#7
b10 Q
1U
1V
b11 =
1"
#8
0"
#9
b11 E
b100000 Q
b0 D
b0 C
1P
1O
0V
0U
b100 =
1"
#10
0"
#11
b11 Q
0P
0O
b101 =
1"
#12
0"
#13
b100 Q
1T
b110 =
1"
#14
0"
#15
b101 E
b100000 Q
1K
1J
0T
b111 =
1"
#16
0"
#17
b100 %
b100 0
b100 \
b101 Q
0K
0J
b1000 =
1"
#18
0"
#19
b110 E
b100000 Q
1P
1O
b1001 =
1"
#20
0"
#21
b110 Q
0P
0O
b1010 =
1"
#22
0"
#23
b1000 E
b111 Q
b0 G
b0 F
b1011 =
1"
#24
0"
#25
b100000 Q
b100 8
b100 g
1P
b100 7
b100 d
1O
b1100 =
1"
#26
0"
#27
b1000 Q
0P
0O
b1101 =
b11111111111111111111111111111111 *
b11111111111111111111111111111111 +
b11111111111111111111111111111111 i
b11111111111111111111111111111111 )
b11111111111111111111111111111111 ,
b11111111111111111111111111111111 f
1"
#28
0"
#29
b0 )
b0 ,
b0 f
b0 *
b0 +
b0 i
b10001 Q
b11111111111111111111111111111111 I
b11111111111111111111111111111111 H
b1110 =
1"
#30
0"
#31
b10010 E
b100000 Q
b0 6
b0 b
1N
b0 5
b0 `
1M
b1111 =
1"
#32
0"
#33
b10010 Q
0N
0M
b10000 =
1"
#34
0"
#35
b10011 Q
b0 X
b0 W
b10001 =
1"
#36
0"
#37
b10100 Q
b0 9
b10010 =
1"
#38
0"
#39
b10101 E
b100000 Q
1L
b10011 =
b1 D
1"
#40
0"
#41
b10101 Q
0L
b10100 =
1"
#42
0"
#43
b10110 Q
b0 :
b10101 =
1"
#44
0"
#45
b10001 Q
b10110 =
1"
#46
0"
#47
b10010 E
b100000 Q
b1 6
b1 b
1N
b1 5
b1 `
1M
b10111 =
1"
#48
0"
#49
b11111111111111111111111111111111 '
b11111111111111111111111111111111 .
b11111111111111111111111111111111 a
b10010 Q
0N
0M
b11000 =
1"
#50
0"
#51
b10011 Q
b11111111111111111111111111111111 W
b11001 =
1"
#52
0"
#53
b10100 Q
b11111111111111111111111111111100 9
b11010 =
1"
#54
0"
#55
b10101 E
b100000 Q
b11111111111111111111111111111100 4
b11111111111111111111111111111100 ]
1L
b11011 =
b10 D
1"
#56
0"
#57
bx &
bx /
bx _
b10101 Q
0L
b11100 =
1"
#58
0"
#59
b10110 Q
bx :
b11101 =
b0 &
b0 /
b0 _
1"
#60
0"
#61
b10001 Q
b11110 =
1"
#62
0"
#63
b10010 E
b100000 Q
b10 6
b10 b
1N
b10 5
b10 `
1M
b11111 =
1"
#64
0"
#65
b1 '
b1 .
b1 a
b10010 Q
0N
0M
b100000 =
1"
#66
0"
#67
b10011 Q
b1 W
b100001 =
1"
#68
0"
#69
b10100 Q
b100 9
b100010 =
1"
#70
0"
#71
b10101 E
b100000 Q
b100 4
b100 ]
1L
b100011 =
b11 D
1"
#72
0"
#73
b11111111111111111111111111111111 &
b11111111111111111111111111111111 /
b11111111111111111111111111111111 _
b10101 Q
0L
b100100 =
1"
#74
0"
#75
b10110 Q
b11111111111111111111111111111111 :
b100101 =
b0 &
b0 /
b0 _
1"
#76
0"
#77
b100 Q
b0 D
1V
b1 A
b1 e
1U
b0 I
b1 H
b100 @
b100 ^
1T
b100110 =
b1 C
1"
#78
0"
#79
b101 E
b100000 Q
b1 3
b1 [
1K
b1 2
b1 Y
1J
0T
0V
0U
b100111 =
1"
#80
0"
#81
b1 $
b1 1
b1 Z
b101 %
b101 0
b101 \
b101 Q
0K
0J
b101000 =
1"
#82
0"
#83
b110 E
b100000 Q
b1 8
b1 g
1P
b1 7
b1 d
1O
b101001 =
1"
#84
0"
#85
b11111111111111111111111111111111 )
b11111111111111111111111111111111 ,
b11111111111111111111111111111111 f
b11111111111111111111111111111111 *
b11111111111111111111111111111111 +
b11111111111111111111111111111111 i
b110 Q
0P
0O
b101010 =
1"
#86
0"
#87
b1000 E
b111 Q
b11111111111111111111111111111111 G
b11111111111111111111111111111111 F
b101011 =
b0 *
b0 +
b0 i
b0 )
b0 ,
b0 f
1"
#88
0"
#89
b100000 Q
b101 8
b101 g
1P
b101 7
b101 d
1O
b101100 =
1"
#90
0"
#91
b1000 Q
0P
0O
b101101 =
b11111111111111111111111111111111 *
b11111111111111111111111111111111 +
b11111111111111111111111111111111 i
b11111111111111111111111111111111 )
b11111111111111111111111111111111 ,
b11111111111111111111111111111111 f
1"
#92
0"
#93
b0 )
b0 ,
b0 f
b0 *
b0 +
b0 i
b1001 Q
b11111111111111111111111111111111 I
b11111111111111111111111111111111 H
b101110 =
1"
#94
0"
#95
b1010 E
b100000 Q
b0 6
b0 b
1N
b0 8
b0 g
1P
b0 5
b0 `
1M
b0 7
b0 d
1O
b101111 =
1"
#96
0"
#97
b0 '
b0 .
b0 a
b1010 Q
0P
0O
0N
0M
b110000 =
1"
#98
0"
#99
b1011 Q
b0 ;
b0 9
b110001 =
1"
#100
0"
#101
b1100 Q
b1 8
b1 g
1V
b0 A
b0 e
b1 7
b1 d
1U
b110010 =
1"
#102
0"
#103
b1101 E
b100000 Q
1P
1O
0V
0U
b110011 =
b1 D
1"
#104
0"
#105
b1101 Q
0P
0O
b110100 =
1"
#106
0"
#107
b1110 Q
b0 W
b110101 =
1"
#108
0"
#109
b1111 E
b100000 Q
b0 4
b0 ]
1L
b110110 =
1"
#110
0"
#111
b1111 Q
0L
b110111 =
1"
#112
0"
#113
b10000 Q
b0 :
b111000 =
1"
#114
0"
#115
b1001 Q
b111001 =
1"
#116
0"
#117
b1010 E
b100000 Q
b1 6
b1 b
1N
b0 8
b0 g
1P
b1 5
b1 `
1M
b0 7
b0 d
1O
b111010 =
1"
#118
0"
#119
b1010 Q
0P
0O
0N
0M
b111011 =
b11111111111111111111111111111111 '
b11111111111111111111111111111111 .
b11111111111111111111111111111111 a
1"
#120
0"
#121
b1011 Q
b11111111111111111111111111111111 9
b111100 =
1"
#122
0"
#123
b1100 Q
b1 8
b1 g
1V
b11111111111111111111111111111111 A
b11111111111111111111111111111111 e
b1 7
b1 d
1U
b111101 =
1"
#124
0"
#125
b1101 E
b100000 Q
1P
1O
0V
0U
b111110 =
b10 D
1"
#126
0"
#127
b1101 Q
0P
0O
b111111 =
b11111111111111111111111111111111 )
b11111111111111111111111111111111 ,
b11111111111111111111111111111111 f
1"
#128
0"
#129
b0 )
b0 ,
b0 f
b1110 Q
b11111111111111111111111111111100 9
b11111111111111111111111111111111 W
b1000000 =
1"
#130
0"
#131
b1111 E
b100000 Q
b11111111111111111111111111111100 4
b11111111111111111111111111111100 ]
1L
b1000001 =
1"
#132
0"
#133
bx &
bx /
bx _
b1111 Q
0L
b1000010 =
1"
#134
0"
#135
b10000 Q
bx :
b1000011 =
b0 &
b0 /
b0 _
1"
#136
0"
#137
b1001 Q
b1000100 =
1"
#138
0"
#139
b1010 E
b100000 Q
b10 6
b10 b
1N
b0 8
b0 g
1P
b10 5
b10 `
1M
b0 7
b0 d
1O
b1000101 =
1"
#140
0"
#141
b1 '
b1 .
b1 a
b1010 Q
0P
0O
0N
0M
b1000110 =
1"
#142
0"
#143
b1011 Q
b1 9
b1000111 =
1"
#144
0"
#145
b1100 Q
b1 8
b1 g
1V
b1 A
b1 e
b1 7
b1 d
1U
b1001000 =
1"
#146
0"
#147
b1101 E
b100000 Q
1P
1O
0V
0U
b1001001 =
b11 D
1"
#148
0"
#149
b1 )
b1 ,
b1 f
b1101 Q
0P
0O
b1001010 =
1"
#150
0"
#151
b1110 Q
b100 9
b1 W
b1001011 =
b0 )
b0 ,
b0 f
1"
#152
0"
#153
b1111 E
b100000 Q
b100 4
b100 ]
1L
b1001100 =
1"
#154
0"
#155
b1111 Q
0L
b1001101 =
b100 &
b100 /
b100 _
1"
#156
0"
#157
b0 &
b0 /
b0 _
b10000 Q
b100 :
b1001110 =
1"
#158
0"
#159
b1001 Q
b1001111 =
1"
#160
0"
#161
b1010 E
b100000 Q
b11 6
b11 b
1N
b0 8
b0 g
1P
b11 5
b11 `
1M
b0 7
b0 d
1O
b1010000 =
1"
#162
0"
#163
b1010 Q
0P
0O
0N
0M
b1010001 =
b11111111111111111111111111111111 (
b11111111111111111111111111111111 -
b11111111111111111111111111111111 c
b0 '
b0 .
b0 a
1"
#164
0"
#165
b1011 Q
b11111111111111111111111111111111 ;
b0 9
b1010010 =
1"
#166
0"
#167
b1100 Q
b11111111111111111111111111111111 B
b11111111111111111111111111111111 h
b1 8
b1 g
1V
b0 A
b0 e
b1 7
b1 d
1U
b1010011 =
1"
#168
0"
#169
b1101 E
b100000 Q
1P
1O
0V
0U
b1010100 =
b100 D
1"
#170
0"
#171
b1101 Q
0P
0O
b1010101 =
b11111111111111111111111111111111 *
b11111111111111111111111111111111 +
b11111111111111111111111111111111 i
1"
#172
0"
#173
b0 *
b0 +
b0 i
b1110 Q
b11111111111111111111111111111111 9
b11111111111111111111111111111111 X
b0 W
b1010110 =
1"
#174
0"
#175
b1111 E
b100000 Q
b11111111111111111111111111111111 4
b11111111111111111111111111111111 ]
1L
b1010111 =
1"
#176
0"
#177
bx &
bx /
bx _
b1111 Q
0L
b1011000 =
1"
#178
0"
#179
b10000 Q
bx :
b1011001 =
b0 &
b0 /
b0 _
1"
#180
0"
#181
b1001 Q
b1011010 =
1"
#182
0"
#183
b1010 E
b100000 Q
b100 6
b100 b
1N
b0 8
b0 g
1P
b100 5
b100 `
1M
b0 7
b0 d
1O
b1011011 =
1"
#184
0"
#185
b1010 Q
0P
0O
0N
0M
b1011100 =
1"
#186
0"
#187
b1011 Q
b0 9
b1011101 =
1"
#188
0"
#189
b1100 Q
b1 8
b1 g
1V
b1 7
b1 d
1U
b1011110 =
1"
#190
0"
#191
b1101 E
b100000 Q
1P
1O
0V
0U
b1011111 =
b101 D
1"
#192
0"
#193
b11111111111111111111111111111111 *
b11111111111111111111111111111111 +
b11111111111111111111111111111111 i
b1101 Q
0P
0O
b1100000 =
1"
#194
0"
#195
b1110 Q
b11111111111111111111111111111111 9
b1100001 =
b0 *
b0 +
b0 i
1"
#196
0"
#197
b1111 E
b100000 Q
1L
b1100010 =
1"
#198
0"
#199
b1111 Q
0L
b1100011 =
bx &
bx /
bx _
1"
#200
0"
#201
b0 &
b0 /
b0 _
b10000 Q
b1100100 =
1"
#202
0"
#203
b1001 Q
b1100101 =
1"
#204
0"
#205
b1010 E
b100000 Q
b101 6
b101 b
1N
b0 8
b0 g
1P
b101 5
b101 `
1M
b0 7
b0 d
1O
b1100110 =
1"
#206
0"
#207
b1010 Q
0P
0O
0N
0M
b1100111 =
b1 (
b1 -
b1 c
b11111111111111111111111111111111 '
b11111111111111111111111111111111 .
b11111111111111111111111111111111 a
1"
#208
0"
#209
b1011 Q
b1 ;
b1101000 =
1"
#210
0"
#211
b1100 Q
b1 B
b1 h
b1 8
b1 g
1V
b11111111111111111111111111111111 A
b11111111111111111111111111111111 e
b1 7
b1 d
1U
b1101001 =
1"
#212
0"
#213
b1101 E
b100000 Q
1P
1O
0V
0U
b1101010 =
b110 D
1"
#214
0"
#215
b1101 Q
0P
0O
b1101011 =
b1 *
b1 +
b1 i
b11111111111111111111111111111111 )
b11111111111111111111111111111111 ,
b11111111111111111111111111111111 f
1"
#216
0"
#217
b0 )
b0 ,
b0 f
b0 *
b0 +
b0 i
b1110 Q
b11111111111111111111111111111101 9
b1 X
b11111111111111111111111111111111 W
b1101100 =
1"
#218
0"
#219
b1111 E
b100000 Q
b11111111111111111111111111111101 4
b11111111111111111111111111111101 ]
1L
b1101101 =
1"
#220
0"
#221
bx &
bx /
bx _
b1111 Q
0L
b1101110 =
1"
#222
0"
#223
b10000 Q
b1101111 =
b0 &
b0 /
b0 _
1"
#224
0"
#225
b1001 Q
b1110000 =
1"
#226
0"
#227
b1010 E
b100000 Q
b110 6
b110 b
1N
b0 8
b0 g
1P
b110 5
b110 `
1M
b0 7
b0 d
1O
b1110001 =
1"
#228
0"
#229
b1 '
b1 .
b1 a
b1010 Q
0P
0O
0N
0M
b1110010 =
1"
#230
0"
#231
b1011 Q
b1 9
b1110011 =
1"
#232
0"
#233
b1100 Q
b1 8
b1 g
1V
b1 A
b1 e
b1 7
b1 d
1U
b1110100 =
1"
#234
0"
#235
b1101 E
b100000 Q
1P
1O
0V
0U
b1110101 =
b111 D
1"
#236
0"
#237
b1 )
b1 ,
b1 f
b1 *
b1 +
b1 i
b1101 Q
0P
0O
b1110110 =
1"
#238
0"
#239
b1110 Q
b101 9
b1 W
b1110111 =
b0 *
b0 +
b0 i
b0 )
b0 ,
b0 f
1"
#240
0"
#241
b1111 E
b100000 Q
b101 4
b101 ]
1L
b1111000 =
1"
#242
0"
#243
b1111 Q
0L
b1111001 =
b11111111111111111111111111111111 &
b11111111111111111111111111111111 /
b11111111111111111111111111111111 _
1"
#244
0"
#245
b0 &
b0 /
b0 _
b10000 Q
b11111111111111111111111111111111 :
b1111010 =
1"
