placement/verilog/sim/memorias/memoryRAM.v
module memoryRAM #(
  parameter init_file = "mem_file.txt",
  parameter data_depth = 4
  )(clk, read, write, addr, dataRead, dataWrite);
  input clk, read, write;
  input signed [32-1:0] addr, dataWrite;
  output reg signed [32-1:0] dataRead;
  reg signed [32-1:0] memRAM [(2**data_depth)-1:0];
  reg [32-1:0] i, j;
  always @ (posedge clk) begin
    dataRead <= 0;
    if(read) begin
      dataRead <= memRAM[addr];
    end
    if(write) begin
      memRAM[addr] <= dataWrite;
    end
    /*$display();
    for(i=0; i<4; i++) begin
			for(j=0; j<4; j++) begin
				$write("%4d", $signed(memRAM[i*4+j]));
			end
		  $display();
    end*/
  end
  initial begin
    dataRead = 0;
    $readmemh(init_file, memRAM, 0, (2**data_depth)-1);
  end
endmodule

placement/verilog/memorias/memoryROM.v
module memoryROM #(
  parameter init_file = "mem_file.txt",
  parameter data_depth = 15
  )(clk, read, addr, data);
  input clk, read;
  input [32-1:0] addr;
  output reg [32-1:0] data;
  reg  [32-1:0] memROM [data_depth-1:0];
  always @ (posedge clk) begin
    if(read) begin
      data <= memROM[addr];
    end
  end
  initial begin
    data = 0;
    $readmemh(init_file, memROM);
  end
endmodule

placement/verilog/sim/placement.v
`include "memorias/memoryROM.v"
`include "memorias/memoryRAM.v"

module placement(out, clk, reset);
	parameter v = 4;
	//Parameters of states:
	parameter init0 = 0, init1 = 1, init2 = 2, init3 = 3;
	parameter reMem0 = 4, reMem1 = 5, reMem2 = 6, reMem3 = 7, reMem4 = 8;
	parameter posA0 = 9, posA1 = 10, posA2 = 11, posA3 = 12, posA4 = 13, posA5 = 14, posA6 = 15, posA7 = 16;
	parameter posB0 = 17, posB1 = 18, posB2 = 19, posB3 = 20, posB4 = 21, posB5 = 22;
	parameter eval0 = 23, eval1 = 24, eval2 = 25, eval3 = 26, eval4 = 27, eval5 = 28, eval6 = 29, eval7 = 30;
	parameter exit = 31, waitState = 32;
	//Parameters of datas:
	parameter n = 4, n_edge = 15, size_offset = 28;
	//Inputs and output:
	input clk, reset;
	output reg out;
	//Controls:
	reg reEA, reEB, reOX, reOY, rePX, rePY, reGrid;
	reg signed [32-1:0] addrEA, addrEB, addrOX, addrOY, addrPX, addrPY, addrGrid;
	wire signed [32-1:0] doutEA, doutEB, doutOX, doutOY, doutPX, doutPY, doutGrid;
	reg wePX, wePY, weGrid;
	reg signed [32-1:0] dinPX, dinPY, dinGrid;
	wire [32-1:0] outPX, outPY, outOX, outOY, outGrid;
	//Regs and wires:
	reg [32-1:0] state, next_state, i, j;
	reg [32-1:0] aux1, aux2, aux3, aux4;
	reg signed [32-1:0] pos_a_X, pos_a_Y, pos_b_X, pos_b_Y;
	wire signed [32-1:0] a, b;
	reg signed [32-1:0] xi, xj;
	reg signed [32-1:0] sum;
	reg signed [32-1:0] diff_pos_x, diff_pos_y;
	//Outputs of memories:
	assign a = doutEA;
	assign b = doutEB;
	assign outPX = doutPX;
	assign outPY = doutPY;
	assign outOX = doutOX;
	assign outOY = doutOY;
	assign outGrid = doutGrid;

	/*
	States [0,3]: Initialization;
	States [4,8]: Read of memories;
	States [9,16]: Position X of A;
	States [17,22]: Position X of B;
	States [23,30]: Evaluation;
	State 31: End;
	OBS.: States 32 = Wait state.
	*/

	always @(posedge clk) begin
		if(reset) begin
			reEA <= 0; addrEA <= 0;
			reEB <= 0; addrEB <= 0;
			reOX <= 0; addrOX <= 0;
			reOY <= 0; addrOY <= 0;
			rePX <= 0; wePX <= 0; addrPX <= 0; dinPX <= 0;
			rePY <= 0; wePY <= 0; addrPY <= 0; dinPY <= 0;
			reGrid <= 0; weGrid <= 0; addrGrid <= 0; dinGrid <= 0;
			state <= 0; next_state <= 0;
			sum <= 0;
		end
		else begin
			reEA <= 0; reEB <= 0;
			reOX <= 0; reOY <= 0;
			rePX <= 0; wePX <= 0;
			rePY <= 0; wePY <= 0;
			reGrid <= 0; weGrid <= 0;
			//State machine:
			case (state)
				init0: begin
					reEA <= 1; addrEA <= 0;
					state <= init1;
				end
				init1: begin
					wePX <= 1; addrPX <= a; dinPX <= 0;
					wePY <= 1; addrPY <= a; dinPY <= 0;
					state <= init2;
				end
				init2: begin
					rePX <= 1; addrPX <= 0;
					rePY <= 1; addrPY <= 0;
					i <= 0;
					j <= 0;
					state <= waitState;
					next_state <= init3;
				end
				init3: begin
					weGrid <= 1; addrGrid <= outPX*n+outPY; dinGrid <= a;
					state <= reMem0;
				end
				reMem0: begin
					if(i == n_edge) begin
						i <= 0;
						state <= eval0;
					end
					else begin
						reEA <= 1; addrEA <= i;
						reEB <= 1; addrEB <= i;
						state <= waitState;
						next_state <= reMem1;
					end
				end
				reMem1: begin
					rePX <= 1; addrPX <= a;
					rePY <= 1; addrPY <= a;
					state <= waitState;
					next_state <= reMem2;
				end
				reMem2: begin
					pos_a_X <= outPX;
					pos_a_Y <= outPY;
					state <= reMem3;
					next_state <= reMem4;
				end
				reMem3: begin
					rePX <= 1; addrPX <= b;
					rePY <= 1; addrPY <= b;
					state <= waitState;
				end
				reMem4: begin
					pos_b_X <= outPX;
					pos_b_Y <= outPY;
					if(i==0) begin
						state <= posB0;
					end
					else begin
						state <= posA0;
					end
				end
				posA0: begin
					if(pos_a_X != -1) begin
	          state <= posB0;
				 		j <= 0;
			  		end
					else begin
						rePX <= 1; addrPX <= i-1;
						reOX <= 1; addrOX <= j;
						rePY <= 1; addrPY <= i-1;
						reOY <= 1; addrOY <= j;
						state <= waitState;
						next_state <= posA1;
					end
				end
				posA1: begin
					aux1 <= outPX + outOX;
					aux3 <= outPY + outOY;
					state <= posA2;
				end
				posA2: begin
					wePX <= 1; addrPX <= a; dinPX <= aux1;
					wePY <= 1; addrPY <= a; dinPY <= aux3;
					state <= posA3;
				end
				posA3: begin
					rePX <= 1; addrPX <= a;
					rePY <= 1; addrPY <= a;
					j++;
					state <= waitState;
					next_state <= posA4;
				end
				posA4: begin
					xi <= outPX;
					xj <= outPY;
					aux1 <= outPX*n+outPY;
					state <= posA5;
				end
				posA5: begin
					reGrid <= 1; addrGrid <= aux1;
					state <= waitState;
					next_state <= posA6;
				end
				posA6: begin
					aux2 <= outGrid;
					state <= posA7;
				end
				posA7: begin
					if(aux2 == -1 && xi < n && xi >= 0 && xj < n && xj >= 0) begin
						weGrid <= 1; addrGrid <= aux1; dinGrid <= a;
						pos_a_X <= xi;
						pos_a_Y <= xj;
						state <= posB0;
						j <= 0;
					end
					else if(pos_a_X == -1) begin
						state <= posA0;
					end
					if(j > size_offset) begin
						$display("No solution\n");
						out <= 0;
						state <= exit;
					end
				end
				posB0: begin
					if(pos_b_X != -1) begin
						state <= reMem0;
						j <= 0;
						i++;
					end
					else begin
						reOX <= 1; addrOX <= j;
						reOY <= 1; addrOY <= j;
						state <= waitState;
						next_state <= posB1;
					end
				end
				posB1: begin
					xi <= pos_a_X + outOX;
					xj <= pos_a_Y + outOY;
					state <= posB2;
				end
				posB2: begin
					aux1 <= xi*n+xj;
					state <= posB3;
				end
				posB3: begin
					j++;
					reGrid <= 1; addrGrid <= aux1;
					state <= waitState;
					next_state <= posB4;
				end
				posB4: begin
					aux2 <= outGrid;
					state <= posB5;
				end
				posB5: begin
					if(aux2 == -1 && xi < n && xi >= 0 && xj < n && xj >= 0) begin
						weGrid <= 1; addrGrid <= aux1; dinGrid <= b;
						pos_b_X <= xi;
						pos_b_Y <= xj;
						wePX <= 1; addrPX <= b; dinPX <= xi;
						wePY <= 1; addrPY <= b; dinPY <= xj;
						j <= 0;
						i++;
						state <= reMem0;
					end
					else if(pos_b_X == -1) begin
						state <= posB0;
					end
					if(j > size_offset) begin
						$display("No solution\n");
						out <= 0;
						state <= exit;
					end
				end
				eval0: begin
					if(i == n_edge) begin
					 	state <= exit;
					end
					else begin
						reEA <= 1; addrEA <= i;
						reEB <= 1; addrEB <= i;
						state <= waitState;
						next_state <= eval1;
					end
				end
				eval1: begin
					rePX <= 1; addrPX <= a;
					rePY <= 1; addrPY <= a;
					state <= waitState;
					next_state <= eval2;
				end
				eval2: begin
					aux1 <= outPX;
					aux2 <= outPY;
					state <= reMem3;
					next_state <= eval3;
				end
				eval3: begin
					aux3 <= outPX;
					aux4 <= outPY;
					state <= eval4;
				end
				eval4: begin
					diff_pos_x <= aux1 - aux3;
					state <= eval5;
				end
				eval5: begin
					if(diff_pos_x < 0) begin
						diff_pos_x <= (diff_pos_x ^ (32'b11111111111111111111111111111111)) + 1;
					end
					diff_pos_y <= aux2 - aux4;
					state <= eval6;
				end
				eval6: begin
					if(diff_pos_y < 0) begin
						diff_pos_y <= (diff_pos_y ^ (32'b11111111111111111111111111111111)) + 1;
					end
					state <= eval7;
				end
				eval7: begin
					sum <= sum + diff_pos_x + diff_pos_y - 1;
					i++;
					state <= eval0;
				end
				exit: begin
					out <= 1;
					$write("\nEvaluation = %1d\n", sum);
					$finish;
				end
				waitState: begin
					state <= next_state;
				end
			endcase
		end
	end
	memoryROM #(.init_file("dados/simple/eaData.txt"), .data_depth(v)) ea (.clk(clk), .read(reEA), .addr(addrEA), .data(doutEA));
	memoryROM #(.init_file("dados/simple/ebData.txt"), .data_depth(v)) eb (.clk(clk), .read(reEB), .addr(addrEB), .data(doutEB));
	memoryROM #(.init_file("dados/offsetXData.txt"), .data_depth(5)) offset_x (.clk(clk), .read(reOX), .addr(addrOX), .data(doutOX));
	memoryROM #(.init_file("dados/offsetYData.txt"), .data_depth(5)) offset_y (.clk(clk), .read(reOY), .addr(addrOY), .data(doutOY));
	memoryRAM #(.init_file("dados/simple/posData.txt"), .data_depth(v)) pos_X (.clk(clk), .read(rePX), .write(wePX), .addr(addrPX), .dataRead(doutPX), .dataWrite(dinPX));
	memoryRAM #(.init_file("dados/simple/posData.txt"), .data_depth(v)) pos_Y (.clk(clk), .read(rePY), .write(wePY), .addr(addrPY), .dataRead(doutPY), .dataWrite(dinPY));
	memoryRAM #(.init_file("dados/gridData.txt"), .data_depth(8)) grid (.clk(clk), .read(reGrid), .write(weGrid), .addr(addrGrid), .dataRead(doutGrid), .dataWrite(dinGrid));
endmodule

module test;
	reg clk;
	reg reset;
	initial begin
		$dumpfile("placement.vcd");
		$dumpvars;
		clk = 0;
		reset = 0;
		#1 reset = 1;
		#2 reset = 0;
	end
	always #1 clk = !clk;
	wire out;
	placement p1 (out, clk, reset);
endmodule

placement/verilog/sim/placement.vcd
$date
	Tue Mar  3 10:04:45 2020
$end
$version
	Icarus Verilog
$end
$timescale
	1s
$end
$scope module test $end
$var wire 1 ! out $end
$var reg 1 " clk $end
$var reg 1 # reset $end
$scope module p1 $end
$var wire 32 $ a [31:0] $end
$var wire 32 % b [31:0] $end
$var wire 1 " clk $end
$var wire 32 & outGrid [31:0] $end
$var wire 32 ' outOX [31:0] $end
$var wire 32 ( outOY [31:0] $end
$var wire 32 ) outPX [31:0] $end
$var wire 32 * outPY [31:0] $end
$var wire 1 # reset $end
$var wire 32 + doutPY [31:0] $end
$var wire 32 , doutPX [31:0] $end
$var wire 32 - doutOY [31:0] $end
$var wire 32 . doutOX [31:0] $end
$var wire 32 / doutGrid [31:0] $end
$var wire 32 0 doutEB [31:0] $end
$var wire 32 1 doutEA [31:0] $end
$var reg 32 2 addrEA [31:0] $end
$var reg 32 3 addrEB [31:0] $end
$var reg 32 4 addrGrid [31:0] $end
$var reg 32 5 addrOX [31:0] $end
$var reg 32 6 addrOY [31:0] $end
$var reg 32 7 addrPX [31:0] $end
$var reg 32 8 addrPY [31:0] $end
$var reg 32 9 aux1 [31:0] $end
$var reg 32 : aux2 [31:0] $end
$var reg 32 ; aux3 [31:0] $end
$var reg 32 < aux4 [31:0] $end
$var reg 32 = diff_pos_x [31:0] $end
$var reg 32 > diff_pos_y [31:0] $end
$var reg 32 ? dinGrid [31:0] $end
$var reg 32 @ dinPX [31:0] $end
$var reg 32 A dinPY [31:0] $end
$var reg 32 B i [31:0] $end
$var reg 32 C j [31:0] $end
$var reg 32 D next_state [31:0] $end
$var reg 1 ! out $end
$var reg 32 E pos_a_X [31:0] $end
$var reg 32 F pos_a_Y [31:0] $end
$var reg 32 G pos_b_X [31:0] $end
$var reg 32 H pos_b_Y [31:0] $end
$var reg 1 I reEA $end
$var reg 1 J reEB $end
$var reg 1 K reGrid $end
$var reg 1 L reOX $end
$var reg 1 M reOY $end
$var reg 1 N rePX $end
$var reg 1 O rePY $end
$var reg 32 P state [31:0] $end
$var reg 32 Q sum [31:0] $end
$var reg 1 R weGrid $end
$var reg 1 S wePX $end
$var reg 1 T wePY $end
$var reg 32 U xi [31:0] $end
$var reg 32 V xj [31:0] $end
$scope module ea $end
$var wire 32 W addr [31:0] $end
$var wire 1 " clk $end
$var wire 1 I read $end
$var reg 32 X data [31:0] $end
$upscope $end
$scope module eb $end
$var wire 32 Y addr [31:0] $end
$var wire 1 " clk $end
$var wire 1 J read $end
$var reg 32 Z data [31:0] $end
$upscope $end
$scope module grid $end
$var wire 32 [ addr [31:0] $end
$var wire 1 " clk $end
$var wire 32 \ dataWrite [31:0] $end
$var wire 1 K read $end
$var wire 1 R write $end
$var reg 32 ] dataRead [31:0] $end
$var reg 32 ^ i [31:0] $end
$var reg 32 _ j [31:0] $end
$upscope $end
$scope module offset_x $end
$var wire 32 ` addr [31:0] $end
$var wire 1 " clk $end
$var wire 1 L read $end
$var reg 32 a data [31:0] $end
$upscope $end
$scope module offset_y $end
$var wire 32 b addr [31:0] $end
$var wire 1 " clk $end
$var wire 1 M read $end
$var reg 32 c data [31:0] $end
$upscope $end
$scope module pos_X $end
$var wire 32 d addr [31:0] $end
$var wire 1 " clk $end
$var wire 32 e dataWrite [31:0] $end
$var wire 1 N read $end
$var wire 1 S write $end
$var reg 32 f dataRead [31:0] $end
$var reg 32 g i [31:0] $end
$var reg 32 h j [31:0] $end
$upscope $end
$scope module pos_Y $end
$var wire 32 i addr [31:0] $end
$var wire 1 " clk $end
$var wire 32 j dataWrite [31:0] $end
$var wire 1 O read $end
$var wire 1 T write $end
$var reg 32 k dataRead [31:0] $end
$var reg 32 l i [31:0] $end
$var reg 32 m j [31:0] $end
$upscope $end
$upscope $end
$upscope $end
$enddefinitions $end
#0
$dumpvars
bx m
bx l
b0 k
bx j
bx i
bx h
bx g
b0 f
bx e
bx d
b0 c
bx b
b0 a
bx `
bx _
bx ^
b0 ]
bx \
bx [
b0 Z
bx Y
b0 X
bx W
bx V
bx U
xT
xS
xR
bx Q
bx P
xO
xN
xM
xL
xK
xJ
xI
bx H
bx G
bx F
bx E
bx D
bx C
bx B
bx A
bx @
bx ?
bx >
bx =
bx <
bx ;
bx :
bx 9
bx 8
bx 7
bx 6
bx 5
bx 4
bx 3
bx 2
b0 1
b0 0
b0 /
b0 .
b0 -
b0 ,
b0 +
b0 *
b0 )
b0 (
b0 '
b0 &
b0 %
b0 $
0#
0"
x!
$end
#1
b0 Q
b0 D
b0 P
b0 ?
b0 \
b0 4
b0 [
0R
0K
b0 A
b0 j
b0 8
b0 i
0T
0O
b0 @
b0 e
b0 7
b0 d
0S
0N
b0 6
b0 b
0M
b0 5
b0 `
0L
b0 3
b0 Y
0J
b0 2
b0 W
0I
b100 h
b100 g
b100 m
b100 l
b1000 _
b1000 ^
1"
1#
#2
0"
#3
b1 P
1I
b1000 _
b1000 ^
b100 m
b100 l
b100 h
b100 g
1"
0#
#4
0"
#5
b10 P
1T
1S
0I
b100 h
b100 g
b100 m
b100 l
b1000 _
b1000 ^
1"
#6
0"
#7
b11 D
b100000 P
b0 C
b0 B
1O
1N
0T
0S
b1000 _
b1000 ^
b100 m
b100 l
b100 h
b100 g
1"
#8
0"
#9
b11 P
0O
0N
b100 h
b100 g
b100 m
b100 l
b1000 _
b1000 ^
1"
#10
0"
#11
b100 P
1R
b1000 _
b1000 ^
b100 m
b100 l
b100 h
b100 g
1"
#12
0"
#13
b101 D
b100000 P
1J
1I
0R
b100 h
b100 g
b100 m
b100 l
b1000 _
b1000 ^
1"
#14
0"
#15
b101 P
0J
0I
b100 %
b100 0
b100 Z
b1000 _
b1000 ^
b100 m
b100 l
b100 h
b100 g
1"
#16
0"
#17
b110 D
b100000 P
1O
1N
b100 h
b100 g
b100 m
b100 l
b1000 _
b1000 ^
1"
#18
0"
#19
b110 P
0O
0N
b1000 _
b1000 ^
b100 m
b100 l
b100 h
b100 g
1"
#20
0"
#21
b1000 D
b111 P
b0 F
b0 E
b100 h
b100 g
b100 m
b100 l
b1000 _
b1000 ^
1"
#22
0"
#23
b100000 P
b100 8
b100 i
1O
b100 7
b100 d
1N
b1000 _
b1000 ^
b100 m
b100 l
b100 h
b100 g
1"
#24
0"
#25
b11111111111111111111111111111111 )
b11111111111111111111111111111111 ,
b11111111111111111111111111111111 f
b11111111111111111111111111111111 *
b11111111111111111111111111111111 +
b11111111111111111111111111111111 k
b1000 P
0O
0N
b100 h
b100 g
b100 m
b100 l
b1000 _
b1000 ^
1"
#26
0"
#27
b10001 P
b11111111111111111111111111111111 H
b11111111111111111111111111111111 G
b0 *
b0 +
b0 k
b0 )
b0 ,
b0 f
b1000 _
b1000 ^
b100 m
b100 l
b100 h
b100 g
1"
#28
0"
#29
b10010 D
b100000 P
1M
1L
b100 h
b100 g
b100 m
b100 l
b1000 _
b1000 ^
1"
#30
0"
#31
b10010 P
0M
0L
b1 (
b1 -
b1 c
b1000 _
b1000 ^
b100 m
b100 l
b100 h
b100 g
1"
#32
0"
#33
b10011 P
b1 V
b0 U
b100 h
b100 g
b100 m
b100 l
b1000 _
b1000 ^
1"
#34
0"
#35
b10100 P
b1 9
b1000 _
b1000 ^
b100 m
b100 l
b100 h
b100 g
1"
#36
0"
#37
b10101 D
b100000 P
b1 4
b1 [
1K
b100 h
b100 g
b100 m
b100 l
b1000 _
b1000 ^
b1 C
1"
#38
0"
#39
b10101 P
0K
b11111111111111111111111111111111 &
b11111111111111111111111111111111 /
b11111111111111111111111111111111 ]
b1000 _
b1000 ^
b100 m
b100 l
b100 h
b100 g
1"
#40
0"
#41
b0 &
b0 /
b0 ]
b10110 P
b11111111111111111111111111111111 :
b100 h
b100 g
b100 m
b100 l
b1000 _
b1000 ^
1"
#42
0"
#43
b100 P
b0 C
b1 A
b1 j
1T
1S
b1 H
b0 G
b100 ?
b100 \
1R
b1 B
b1000 _
b1000 ^
b100 m
b100 l
b100 h
b100 g
1"
#44
0"
#45
b101 D
b100000 P
b1 3
b1 Y
1J
b1 2
b1 W
1I
0R
0T
0S
b100 h
b100 g
b100 m
b100 l
b1000 _
b1000 ^
1"
#46
0"
#47
b101 P
0J
0I
b101 %
b101 0
b101 Z
b1 $
b1 1
b1 X
b1000 _
b1000 ^
b100 m
b100 l
b100 h
b100 g
1"
#48
0"
#49
b110 D
b100000 P
b1 8
b1 i
1O
b1 7
b1 d
1N
b100 h
b100 g
b100 m
b100 l
b1000 _
b1000 ^
1"
#50
0"
#51
b110 P
0O
0N
b11111111111111111111111111111111 *
b11111111111111111111111111111111 +
b11111111111111111111111111111111 k
b11111111111111111111111111111111 )
b11111111111111111111111111111111 ,
b11111111111111111111111111111111 f
b1000 _
b1000 ^
b100 m
b100 l
b100 h
b100 g
1"
#52
0"
#53
b0 )
b0 ,
b0 f
b0 *
b0 +
b0 k
b1000 D
b111 P
b11111111111111111111111111111111 F
b11111111111111111111111111111111 E
b100 h
b100 g
b100 m
b100 l
b1000 _
b1000 ^
1"
#54
0"
#55
b100000 P
b101 8
b101 i
1O
b101 7
b101 d
1N
b1000 _
b1000 ^
b100 m
b100 l
b100 h
b100 g
1"
#56
0"
#57
b11111111111111111111111111111111 )
b11111111111111111111111111111111 ,
b11111111111111111111111111111111 f
b11111111111111111111111111111111 *
b11111111111111111111111111111111 +
b11111111111111111111111111111111 k
b1000 P
0O
0N
b100 h
b100 g
b100 m
b100 l
b1000 _
b1000 ^
1"
#58
0"
#59
b1001 P
b11111111111111111111111111111111 H
b11111111111111111111111111111111 G
b0 *
b0 +
b0 k
b0 )
b0 ,
b0 f
b1000 _
b1000 ^
b100 m
b100 l
b100 h
b100 g
1"
#60
0"
#61
b1010 D
b100000 P
1M
b0 8
b0 i
1O
1L
b0 7
b0 d
1N
b100 h
b100 g
b100 m
b100 l
b1000 _
b1000 ^
1"
#62
0"
#63
b1010 P
0O
0N
0M
0L
b1000 _
b1000 ^
b100 m
b100 l
b100 h
b100 g
1"
#64
0"
#65
b1011 P
b1 ;
b0 9
b100 h
b100 g
b100 m
b100 l
b1000 _
b1000 ^
1"
#66
0"
#67
b1100 P
b1 8
b1 i
1T
b1 7
b1 d
1S
b1000 _
b1000 ^
b100 m
b100 l
b100 h
b100 g
1"
#68
0"
#69
b1101 D
b100000 P
1O
1N
0T
0S
b100 h
b100 g
b100 m
b100 l
b1000 _
b1000 ^
b1 C
1"
#70
0"
#71
b1101 P
0O
0N
b1 *
b1 +
b1 k
b1000 _
b1000 ^
b100 m
b100 l
b100 h
b100 g
1"
#72
0"
#73
b0 *
b0 +
b0 k
b1110 P
b1 9
b100 h
b100 g
b100 m
b100 l
b1000 _
b1000 ^
1"
#74
0"
#75
b1111 D
b100000 P
1K
b1000 _
b1000 ^
b100 m
b100 l
b100 h
b100 g
1"
#76
0"
#77
b100 &
b100 /
b100 ]
b1111 P
0K
b100 h
b100 g
b100 m
b100 l
b1000 _
b1000 ^
1"
#78
0"
#79
b10000 P
b100 :
b0 &
b0 /
b0 ]
b1000 _
b1000 ^
b100 m
b100 l
b100 h
b100 g
1"
#80
0"
#81
b1001 P
b100 h
b100 g
b100 m
b100 l
b1000 _
b1000 ^
1"
#82
0"
#83
b1010 D
b100000 P
b1 6
b1 b
1M
b0 8
b0 i
1O
b1 5
b1 `
1L
b0 7
b0 d
1N
b1000 _
b1000 ^
b100 m
b100 l
b100 h
b100 g
1"
#84
0"
#85
b1 '
b1 .
b1 a
b0 (
b0 -
b0 c
b1010 P
0O
0N
0M
0L
b100 h
b100 g
b100 m
b100 l
b1000 _
b1000 ^
1"
#86
0"
#87
b1011 P
b0 ;
b1000 _
b1000 ^
b100 m
b100 l
b100 h
b100 g
1"
#88
0"
#89
b1100 P
b0 A
b0 j
b1 8
b1 i
1T
b1 @
b1 e
b1 7
b1 d
1S
b100 h
b100 g
b100 m
b100 l
b1000 _
b1000 ^
1"
#90
0"
#91
b1101 D
b100000 P
1O
1N
0T
0S
b10 C
b1000 _
b1000 ^
b100 m
b100 l
b100 h
b100 g
1"
#92
0"
#93
b1 )
b1 ,
b1 f
b1101 P
0O
0N
b100 h
b100 g
b100 m
b100 l
b1000 _
b1000 ^
1"
#94
0"
#95
b1110 P
b100 9
b0 V
b1 U
b0 )
b0 ,
b0 f
b1000 _
b1000 ^
b100 m
b100 l
b100 h
b100 g
1"
#96
0"
#97
b1111 D
b100000 P
b100 4
b100 [
1K
b100 h
b100 g
b100 m
b100 l
b1000 _
b1000 ^
1"
#98
0"
#99
b1111 P
0K
b11111111111111111111111111111111 &
b11111111111111111111111111111111 /
b11111111111111111111111111111111 ]
b1000 _
b1000 ^
b100 m
b100 l
b100 h
b100 g
1"
#100
0"
#101
b0 &
b0 /
b0 ]
b10000 P
b11111111111111111111111111111111 :
b100 h
b100 g
b100 m
b100 l
b1000 _
b1000 ^
1"
#102
0"
#103
b0 C
b10001 P
b0 F
b1 E
b1 ?
b1 \
1R
b1000 _
b1000 ^
b100 m
b100 l
b100 h
b100 g
1"
#104
0"
#105
b10010 D
b100000 P
b0 6
b0 b
1M
b0 5
b0 `
1L
0R
b100 h
b100 g
b100 m
b100 l
b1000 _
b1000 ^
1"
#106
0"
#107
b10010 P
0M
0L
b1 (
b1 -
b1 c
b0 '
b0 .
b0 a
b1000 _
b1000 ^
b100 m
b100 l
b100 h
b100 g
1"
#108
0"
#109
b10011 P
b1 V
b100 h
b100 g
b100 m
b100 l
b1000 _
b1000 ^
1"
#110
0"
#111
b10100 P
b101 9
b1000 _
b1000 ^
b100 m
b100 l
b100 h
b100 g
1"
#112
0"
#113
b10101 D
b100000 P
b101 4
b101 [
1K
b100 h
b100 g
b100 m
b100 l
b1000 _
b1000 ^
b1 C
1"
#114
0"
#115
b10101 P
0K
b11111111111111111111111111111111 &
b11111111111111111111111111111111 /
b11111111111111111111111111111111 ]
b1000 _
b1000 ^
b100 m
b100 l
b100 h
b100 g
1"
#116
0"
#117
b0 &
b0 /
b0 ]
b10110 P
b100 h
b100 g
b100 m
b100 l
b1000 _
b1000 ^
1"
#118
0"
#119
b100 P
b0 C
b1 A
b1 j
b101 8
b101 i
1T
b101 7
b101 d
1S
b1 H
b1 G
b101 ?
b101 \
1R
b10 B
b1000 _
b1000 ^
b100 m
b100 l
b100 h
b100 g
1"
#120
0"
#121
b101 D
b100000 P
b10 3
b10 Y
1J
b10 2
b10 W
1I
0R
0T
0S
b100 h
b100 g
b100 m
b100 l
b1000 _
b1000 ^
1"
#122
0"
#123
b101 P
0J
0I
b110 %
b110 0
b110 Z
b10 $
b10 1
b10 X
b1000 _
b1000 ^
b100 m
b100 l
b100 h
b100 g
1"
#124
0"
#125
b110 D
b100000 P
b10 8
b10 i
1O
b10 7
b10 d
1N
b100 h
b100 g
b100 m
b100 l
b1000 _
b1000 ^
1"
#126
0"
#127
b110 P
0O
0N
b11111111111111111111111111111111 *
b11111111111111111111111111111111 +
b11111111111111111111111111111111 k
b11111111111111111111111111111111 )
b11111111111111111111111111111111 ,
b11111111111111111111111111111111 f
b1000 _
b1000 ^
b100 m
b100 l
b100 h
b100 g
1"
#128
0"
#129
b0 )
b0 ,
b0 f
b0 *
b0 +
b0 k
b1000 D
b111 P
b11111111111111111111111111111111 F
b11111111111111111111111111111111 E
b100 h
b100 g
b100 m
b100 l
b1000 _
b1000 ^
1"
#130
0"
#131
b100000 P
b110 8
b110 i
1O
b110 7
b110 d
1N
b1000 _
b1000 ^
b100 m
b100 l
b100 h
b100 g
1"
#132
0"
#133
b11111111111111111111111111111111 )
b11111111111111111111111111111111 ,
b11111111111111111111111111111111 f
b11111111111111111111111111111111 *
b11111111111111111111111111111111 +
b11111111111111111111111111111111 k
b1000 P
0O
0N
b100 h
b100 g
b100 m
b100 l
b1000 _
b1000 ^
1"
#134
0"
#135
b1001 P
b11111111111111111111111111111111 H
b11111111111111111111111111111111 G
b0 *
b0 +
b0 k
b0 )
b0 ,
b0 f
b1000 _
b1000 ^
b100 m
b100 l
b100 h
b100 g
1"
#136
0"
#137
b1010 D
b100000 P
1M
b1 8
b1 i
1O
1L
b1 7
b1 d
1N
b100 h
b100 g
b100 m
b100 l
b1000 _
b1000 ^
1"
#138
0"
#139
b1010 P
0O
0N
0M
0L
b1 )
b1 ,
b1 f
b1000 _
b1000 ^
b100 m
b100 l
b100 h
b100 g
1"
#140
0"
#141
b0 )
b0 ,
b0 f
b1011 P
b1 ;
b1 9
b100 h
b100 g
b100 m
b100 l
b1000 _
b1000 ^
1"
#142
0"
#143
b1100 P
b10 8
b10 i
1T
b10 7
b10 d
1S
b1000 _
b1000 ^
b100 m
b100 l
b100 h
b100 g
1"
#144
0"
#145
b1101 D
b100000 P
1O
1N
0T
0S
b100 h
b100 g
b100 m
b100 l
b1000 _
b1000 ^
b1 C
1"
#146
0"
#147
b1101 P
0O
0N
b1 *
b1 +
b1 k
b1 )
b1 ,
b1 f
b1000 _
b1000 ^
b100 m
b100 l
b100 h
b100 g
1"
#148
0"
#149
b0 )
b0 ,
b0 f
b0 *
b0 +
b0 k
b1110 P
b101 9
b100 h
b100 g
b100 m
b100 l
b1000 _
b1000 ^
1"
#150
0"
#151
b1111 D
b100000 P
1K
b1000 _
b1000 ^
b100 m
b100 l
b100 h
b100 g
1"
#152
0"
#153
b101 &
b101 /
b101 ]
b1111 P
0K
b100 h
b100 g
b100 m
b100 l
b1000 _
b1000 ^
1"
#154
0"
#155
b10000 P
b101 :
b0 &
b0 /
b0 ]
b1000 _
b1000 ^
b100 m
b100 l
b100 h
b100 g
1"
#156
0"
#157
b1001 P
b100 h
b100 g
b100 m
b100 l
b1000 _
b1000 ^
1"
#158
0"
#159
b1010 D
b100000 P
b1 6
b1 b
1M
b1 8
b1 i
1O
b1 5
b1 `
1L
b1 7
b1 d
1N
b1000 _
b1000 ^
b100 m
b100 l
b100 h
b100 g
1"
#160
0"
#161
b1 '
b1 .
b1 a
b0 (
b0 -
b0 c
b1 )
b1 ,
b1 f
b1010 P
0O
0N
0M
0L
b100 h
b100 g
b100 m
b100 l
b1000 _
b1000 ^
1"
#162
0"
#163
b1011 P
b0 ;
b10 9
b0 )
b0 ,
b0 f
b1000 _
b1000 ^
b100 m
b100 l
b100 h
b100 g
1"
#164
0"
#165
b1100 P
b0 A
b0 j
b10 8
b10 i
1T
b10 @
b10 e
b10 7
b10 d
1S
b100 h
b100 g
b100 m
b100 l
b1000 _
b1000 ^
1"
#166
0"
#167
b1101 D
b100000 P
1O
1N
0T
0S
b10 C
b1000 _
b1000 ^
b100 m
b100 l
b100 h
b100 g
1"
#168
0"
#169
b10 )
b10 ,
b10 f
b1101 P
0O
0N
b100 h
b100 g
b100 m
b100 l
b1000 _
b1000 ^
1"
#170
0"
#171
b1110 P
b1000 9
b0 V
b10 U
b0 )
b0 ,
b0 f
b1000 _
b1000 ^
b100 m
b100 l
b100 h
b100 g
1"
#172
0"
#173
b1111 D
b100000 P
b1000 4
b1000 [
1K
b100 h
b100 g
b100 m
b100 l
b1000 _
b1000 ^
1"
#174
0"
#175
b1111 P
0K
b11111111111111111111111111111111 &
b11111111111111111111111111111111 /
b11111111111111111111111111111111 ]
b1000 _
b1000 ^
b100 m
b100 l
b100 h
b100 g
1"
#176
0"
